Workbook

Sheet 00_Read_Me
A1: The Hermes Way
A2: The working database for what 'Hermes, fully realized' actually means — built 2026-10-03, meant to keep growing.
A4: WHAT THIS WORKBOOK IS
A5: A flat, execution-level inventory of every feature required to realize Hermes as a complete personal-agent
A6: platform — organized by capability domain (tabs 01-15), not by phase or timeline. Each row is one concrete,
A7: checkable thing. This is the working feature backlog, not the authoritative record — per this project's
A8: CLAUDE.md, the catalog (Postgres + PostgREST at 192.168.40.2:3003, tagged 'hermes') is the single source of
A9: truth for decisions and facts. Keep this workbook consistent with the catalog; when they disagree, the
A10: catalog wins and this file should be corrected.
A12: THE ONE RULE EVERYTHING IS CHECKED AGAINST
A13: Hermes = hermes-vps. The home network (w_workstation, WireGuard, the local LLM, Salt, MeshCentral) is a
A14: swappable CAPABILITY PROVIDER Hermes reaches over a tunnel — never a place Hermes itself runs, and never a
... A85: Found 2026-10-05: processed a 255-page community practitioner reference and hermesbible.com's bulk-downloadable llms-full.txt (D8_Advanced_Reference). Corrected TM-07 (Nous Tool Gateway is 4 Portal-gated tools, not '5 exec backends' -- that's actually the 7 terminal backends). Found a 4th self-improvement mechanism (GEPA, offline skill evolution via companion repo) and a real credential-protection stack (hermes egress / iron-proxy + Bitwarden, Docker-backend only, matches CR-17). Flagged a verification gap on CR-03 (systemd linger required for true reboot survival, not just logout) and closed the open blockers on IM-01 (SOUL.md template) and IA-05 (exact verified Telegram sequence). User decided: SSH access for execution (new CR-18, not yet provided), Home Assistant existence left open (new HN-09), voice interface explicitly deferred (IA-08).

Sheet 00_Hermes_Way_Standards
A1: The Hermes Way — Standards
A2: The principles every row in tabs 01-15 is checked against. Re-run this check whenever a new capability is added.
A4: # | B4: Standard | C4: What it means in practice | D4: Currently honored? | E4: Current gap, if any | F4: Owned by
A5: 1 | B5: Single source of truth for identity & state | C5: One memory, one identity, reachable identically from every interface — no split-brain between web UI / Desktop / future Telegram. | D5: No | E5: 02_Identity_Memory — session store not confirmed single, SOUL.md/MEMORY.md/USER.md not even committed yet | F5: Hermes Design Specialist
A6: 2 | B6: Core/capability separation | C6: Hermes's core (identity, routing, tools, web presence) lives only on hermes-vps. The home network is a capability provider, swappable without breaking the core. | D6: Partial | E6: 06_Home_Network_Boundary — Salt/MeshCentral added beyond the 2026-09-23 'local LLM only' decision | F6: Hermes Design Specialist
A7: 3 | B7: Graceful degradation, fail-safe default | C7: Losing any optional capability (local model, WireGuard link) degrades to a known-good fallback automatically — never an error, never silent wrong answers. | D7: Unverified | E7: 03_Model_Routing_Resilience MR-05 — the WireGuard-down fire drill has never actually been run | F7: Model/Routing Engineer
A8: 4 | B8: Least privilege | C8: Every credential and tool scoped to the minimum it needs. salt-hermes-infra (no wheel/runner) is the model to copy everywhere else. | D8: Partial | E8: 04_Tool_MCP_Layer TM-11, 12_Security_Hardening SH-04 — only Salt's scope has actually been reviewed this way | F8: Security Reviewer
A9: 5 | B9: One deployment per capability | C9: A given tool/capability exists in exactly one place. No copy-per-environment to keep in sync by hand. | D9: No | E9: vault_mcp.py is deployed 4x (hermes-vps, Claude Code, Codex, project .codex) — see TM-06 / SV-12 | F9: Hermes Design Specialist
A10: 6 | B10: Reproducible, not hand-built | C10: Infra/config changes are scripted and repeatable, not one-off manual edits nobody can redo identically. | D10: Partial | E10: 01_Core_Runtime CR-13 — a raw YAML parse+dump already silently destroyed config.yaml's comments once | F10: Platform/SRE
A11: 7 | B11: Secrets never in plaintext at rest outside the vault | C11: Every real credential lives only in the vault; config files and shares hold no plaintext secrets. | D11: No | E11: 05_Secrets_Vault SV-08 — /Dockers share exposes every container's .env in plaintext by design | F11: Secrets Custodian
A12: 8 | B12: Observable without SSH | C12: Every critical path (tunnel, local model, gateway, VPS) has a health signal a human can see without logging into a box. | D12: No | E12: 09_Observability — no alerting or dashboard exists for any of these yet | F12: Observability
A13: 9 | B13: Backups are tested, not just taken | C13: A backup that's never been restored is a hypothesis. | D13: No | E13: 10_Backup_DR BD-05 — no restore has ever been tested, and hermes-vps itself isn't backed up at all (BD-02) | F13: Platform/SRE
A14: 10 | B14: Repeatable promotion path for new capabilities | C14: Turning a home-network resource into a Hermes tool follows a documented playbook, not ad hoc judgment each time. | D14: No | E14: 04_Tool_MCP_Layer TM-10, 13_Governance GV-01 — no playbook written yet | F14: Hermes Design Specialist
A15: 11 | B15: Cost is visible and bounded | C15: Spend on every paid tier (Codex, Modal) is visible and capped, not discovered after the fact. | D15: Partial | E15: 11_Cost_Subscriptions CS-04/CS-05 — Vultr and Plus are known; Modal and a total rollup are not | F15: Product Owner (Mark)
A16: 12 | B16: Exposure is reviewed before it goes live, not after | C16: New network/tool exposure gets a security pass before shipping, not a retroactive audit. | D16: No | E16: 12_Security_Hardening SH-02 — the gateway's unauthenticated-shell combination shipped and is still live | F16: Security Reviewer
A17: 13 | B17: Changes are tracked | C17: Who changed hermes-vps's config, and when, is recorded somewhere durable. | D17: No | E17: 13_Governance_Change_Mgmt GV-03 — no change log exists | F17: Hermes Design Specialist

Sheet 00_Roles
A1: Roles
A2: One person (you) plays all of these today — naming them separately keeps 'who approves this' and 'who's affected by this' distinct.
A4: Role | B4: Charter | C4: Decides / owns | D4: Tabs where this role appears most
A5: Hermes Design Specialist | B5: Guards architectural coherence — the one role whose job is to keep asking 'does this belong on the VPS or the home network, and does it match the Hermes Way standards.' Reviews any new capability BEFORE it's built, not after. | C5: Where a capability lives; whether scope creep (like Salt/MeshCentral) gets ratified or rolled back; final call on anything tagged Violation. | D5: 00_Hermes_Way_Standards, 02_Identity_Memory, 06_Home_Network_Boundary, 13_Governance
A6: Platform / SRE | B6: Keeps hermes-vps itself alive, patched, backed up, and reproducible. | C6: VPS infra, Dokploy, systemd services, backup/restore, patch cadence. | D6: 01_Core_Runtime, 10_Backup_DR
A7: Secrets Custodian | B7: Owns the vault end to end — what's in it, what's still outside it, rotation. | C7: What gets vaulted, in what order, and the rotation policy. | D7: 05_Secrets_Vault
A8: Model / Routing Engineer | B8: Owns the local-vs-Codex decision logic and the local runtime itself. | C8: Runtime/model choice on w_workstation; routing/judge behavior; the WireGuard-down fire drill. | D8: 03_Model_Routing_Resilience, 07_Local_Inference
A9: Security Reviewer | B9: Finds and closes exposure — the role that would have flagged the gateway shell-access combo before it shipped. | C9: Network exposure, least-privilege scoping, incident response. | D9: 06_Home_Network_Boundary, 12_Security_Hardening
A10: Home-Network Liaison | B10: Represents the home network's interests as a capability provider — keeps it from quietly becoming a second place Hermes 'lives.' | C10: What crosses the WireGuard tunnel and why; Salt/MeshCentral scope. | D10: 06_Home_Network_Boundary, 07_Local_Inference, 04_Tool_MCP_Layer
A11: Interface Engineer | B11: Owns every door into Hermes — web UI, Desktop, Telegram — and that they all lead to the same place. | C11: Auth mechanism, channel rollout, cross-interface continuity testing. | D11: 08_Interfaces_Access
A12: Observability | B12: Makes sure state is visible without SSH. | C12: What gets logged, alerted, and dashboarded. | D12: 09_Observability
A13: Product Owner (Mark) | B13: Final authority — approves spend, approves the finish line, decides when Claude Pro actually gets canceled. | C13: Budget, go/no-go on CS-03, which open risks are acceptable to carry. | D13: 00_Scorecard, 11_Cost_Subscriptions

Sheet 00_Scorecard
A1: Scorecard — the point-based finish line
A2: Points reflect how load-bearing a row is, not effort. Earned points update automatically as Status changes on each tab.
A4: Tab | B4: Domain | C4: Total Points | D4: Points Earned | E4: % Complete
A5: 01_Core_Runtime | B5: Hermes Core Runtime | C5: =SUM('01_Core_Runtime'!G5:G51) | D5: =SUM('01_Core_Runtime'!H5:H51) | E5: =IFERROR(D5/C5,0)
A6: 02_Identity_Memory | B6: Identity & Memory Continuity | C6: =SUM('02_Identity_Memory'!G5:G43) | D6: =SUM('02_Identity_Memory'!H5:H43) | E6: =IFERROR(D6/C6,0)
A7: 03_Model_Routing_Resilience | B7: Model, Provider & Resilience | C7: =SUM('03_Model_Routing_Resilience'!G5:G47) | D7: =SUM('03_Model_Routing_Resilience'!H5:H47) | E7: =IFERROR(D7/C7,0)
A8: 04_Tool_MCP_Layer | B8: Tool / MCP Capability Layer | C8: =SUM('04_Tool_MCP_Layer'!G5:G48) | D8: =SUM('04_Tool_MCP_Layer'!H5:H48) | E8: =IFERROR(D8/C8,0)
A9: 05_Secrets_Vault | B9: Secrets & Vault | C9: =SUM('05_Secrets_Vault'!G5:G49) | D9: =SUM('05_Secrets_Vault'!H5:H49) | E9: =IFERROR(D9/C9,0)
A10: 06_Home_Network_Boundary | B10: Home-Network Capability Boundary | C10: =SUM('06_Home_Network_Boundary'!G5:G42) | D10: =SUM('06_Home_Network_Boundary'!H5:H42) | E10: =IFERROR(D10/C10,0)
A11: 07_Local_Inference | B11: Local Inference Tier | C11: =SUM('07_Local_Inference'!G5:G46) | D11: =SUM('07_Local_Inference'!H5:H46) | E11: =IFERROR(D11/C11,0)
A12: 08_Interfaces_Access | B12: Interfaces & Access Paths | C12: =SUM('08_Interfaces_Access'!G5:G44) | D12: =SUM('08_Interfaces_Access'!H5:H44) | E12: =IFERROR(D12/C12,0)
A13: 09_Observability | B13: Observability | C13: =SUM('09_Observability'!G5:G40) | D13: =SUM('09_Observability'!H5:H40) | E13: =IFERROR(D13/C13,0)
A14: 10_Backup_DR | B14: Backup & Disaster Recovery | C14: =SUM('10_Backup_DR'!G5:G40) | D14: =SUM('10_Backup_DR'!H5:H40) | E14: =IFERROR(D14/C14,0)
A15: 11_Cost_Subscriptions | B15: Cost & Subscriptions | C15: =SUM('11_Cost_Subscriptions'!G5:G40) | D15: =SUM('11_Cost_Subscriptions'!H5:H40) | E15: =IFERROR(D15/C15,0)
A16: 12_Security_Hardening | B16: Security & Hardening | C16: =SUM('12_Security_Hardening'!G5:G42) | D16: =SUM('12_Security_Hardening'!H5:H42) | E16: =IFERROR(D16/C16,0)
A17: 13_Governance_Change_Mgmt | B17: Governance & Change Management | C17: =SUM('13_Governance_Change_Mgmt'!G5:G40) | D17: =SUM('13_Governance_Change_Mgmt'!H5:H40) | E17: =IFERROR(D17/C17,0)
A18: 14_Claude_Code_Parity | B18: Claude Code → Hermes Parity | C18: =SUM('14_Claude_Code_Parity'!G5:G46) | D18: =SUM('14_Claude_Code_Parity'!H5:H46) | E18: =IFERROR(D18/C18,0)
A19: 15_Productivity_And_Acceptance | B19: Productivity & Acceptance Testing | C19: =SUM('15_Productivity_And_Acceptance'!G5:G46) | D19: =SUM('15_Productivity_And_Acceptance'!H5:H46) | E19: =IFERROR(D19/C19,0)
A20: GRAND TOTAL | C20: =SUM(C5:C19) | D20: =SUM(D5:D19) | E20: =IFERROR(D20/C20,0)
A22: FINISH LINE
A23: Hermes is 'fully realized' when ALL of the following are true at once — not just an overall percentage:
A24: 1. Grand Total % Complete above is 100%, or every remaining open row has a deliberate, written decision to leave it for later.
A25: 2. 03_Model_Routing_Resilience row MR-05 (WireGuard-down fire drill) is Done — this is the actual proof of the core promise.
A26: 3. 02_Identity_Memory rows IM-01 through IM-04 are Done — same Hermes, every interface, every location.
A27: 4. 14_Claude_Code_Parity row CCP-12 is Done — Hermes can maintain this project itself, so Claude Code's bootstrap role actually ends, not just gets described as temporary.
A28: 5. Only then: 11_Cost_Subscriptions CS-03 (cancel Claude Pro) gets executed.
A30: LEGACY GOALS (catalog G1-G9) MAPPED TO THIS WORKBOOK
A31: Goal | B31: Catalog status | C31: Detail
A33: G1 — Hermes <-> local model, one real exchange | B33: in_progress | C33: Required: confirmed reachable + one real exchange with the local model. Lives in 03_Model_Routing_Resilience; will need re-verification once 07_Local_Inference's runtime changes.
A34: G2 — local runtime serving multiple models concurrently | B34: done (stale) | C34: Required: verified on Ollama, multiple qwen3-vl variants loaded. Lives in 07_Local_Inference LI-03/LI-04 — must be re-proven on whichever runtime replaces Ollama.
A35: G3 — VPS provisioned, hermes serve running | B35: done | C35: Required: box up, agent process live. Lives in 01_Core_Runtime CR-01 to CR-03.
A36: G4 — WireGuard tunnel, LAN reachable from VPS | B36: done | C36: Required: tunnel + subnet routing, verified end-to-end. Lives in 06_Home_Network_Boundary HN-01/HN-02.
A37: G5 — ChatGPT Plus linked, Codex used for real task | B37: done | C37: Required: native link+code flow, one real coding task. Lives in 03_Model_Routing_Resilience MR-01.
A38: G6 — Hermes Desktop on laptop, same experience 2 locations | B38: not_started | C38: Required: Desktop pointed at VPS backend, proven identical from two places. Lives in 08_Interfaces_Access IA-03/IA-04, blocked on 02_Identity_Memory IM-03.
A39: G7 — Telegram wired up | B39: not_started | C39: Required: a real messaging channel on top of hermes-gateway. Lives in 08_Interfaces_Access IA-05.
A40: G8 — local-first routing verified end-to-end | B40: not_started (likely already true, never marked) | C40: Required: one prompt stays local, one escalates, both observed. The router-llm-as-judge-rebuild-2026-09-28 catalog entry already shows this happened — update the catalog goal's status field to match.
A41: G9 — Claude Pro canceled | B41: not_started | C41: Required: cancel once ChatGPT Plus/Codex covers the same ground. Lives in 11_Cost_Subscriptions CS-03 — the literal finish line.

Sheet 01_Core_Runtime
A1: Hermes Core Runtime
A2: What IS Hermes — must run on hermes-vps only, never on a home box or a laptop.
A4: ID | B4: Feature | C4: Description (execution level) | D4: Must Live On | E4: Status | F4: Evidence / Location | G4: Points | H4: Points Earned | I4: Owner Role | J4: Notes / Next Action
A5: CR-01 | B5: VPS provisioned | C5: Vultr High Performance AMD, Dallas TX — 2 vCPU / 4GB RAM / 100GB NVMe. | D5: Hermes-VPS | E5: Done | F5: hermes-vps live host | G5: 5 | H5: =IF(E5="Done",G5,IF(E5="Partial",G5*0.5,0)) | I5: Platform/SRE
A6: CR-02 | B6: HermesAgent installed on a supported channel | C6: Originally v0.19.0 via pip/uv-tool (unsupported channel, 7 versions behind, vulnerable to CVE-2026-71963 RCE). Migrated 2026-09-29 to the supported install.sh/git channel, now v0.21.5+ — RCE fixed, all dependency CVEs cleared, re-verified end-to-end post-migration. | D6: Hermes-VPS | E6: Done | F6: hermes-migrated-to-supported-install-2026-09-29 | G6: 5 | H6: =IF(E6="Done",G6,IF(E6="Partial",G6*0.5,0)) | I6: Platform/SRE
A7: CR-03 | B7: hermes-gateway running persistently | C7: systemd service, survives reboot, no login dependency. | D7: Hermes-VPS | E7: Done | F7: hermes-gateway.service (system-level unit, /etc/systemd/system, multi-user.target.wants) + real reboot 2026-10-05 17:5x UTC: active again at 17:57:00 with no login session (who=empty), dashboard HTTP 302 reachable | G7: 8 | H7: =IF(E7="Done",G7,IF(E7="Partial",G7*0.5,0)) | I7: Platform/SRE | J7: VERIFIED 2026-10-05: confirmed it's a system-level unit (not systemctl --user), so Linger was not actually load-bearing here (enabled it anyway on hermes user, harmless). Performed a real `reboot` of hermes-vps; service came back active automatically with zero logged-in sessions, dashboard responded post-boot. Reboot survival genuinely confirmed, not just systemctl status.
A8: CR-04 | B8: VPS firewall active | C8: Real firewall rules in place (previously none at all). | D8: Hermes-VPS | E8: Done | F8: hermes-vps ufw/iptables | G8: 8 | H8: =IF(E8="Done",G8,IF(E8="Partial",G8*0.5,0)) | I8: Security Reviewer
A9: CR-05 | B9: Docker + Dokploy installed | C9: Dokploy's own Traefik disabled to avoid conflicting with Caddy on 80/443. | D9: Hermes-VPS | E9: Done | F9: hermes-vps, Dokploy panel :3000 localhost-only | G9: 8 | H9: =IF(E9="Done",G9,IF(E9="Partial",G9*0.5,0)) | I9: Platform/SRE
A10: CR-06 | B10: Dokploy admin credential in vault | C10: Panel login currently wherever it was set at install, not confirmed migrated. | D10: Hermes-VPS | E10: Done | F10: vault: hermes-vps-dokploy-admin (mark.stephen.guy@gmail.com), first-run signup completed 2026-10-06, session verified via /api/auth/get-session | G10: 5 | H10: =IF(E10="Done",G10,IF(E10="Partial",G10*0.5,0)) | I10: Secrets Custodian | J10: Dokploy had zero users - completed first-run signup via its /api/auth/sign-up/email API directly, verified session is valid.
A11: CR-07 | B11: Dokploy exercised end-to-end | C11: Prove Hermes can actually deploy/manage a real container via Dokploy, not just have it installed. | D11: Hermes-VPS | E11: Done | F11: Dokploy project 'hermes-cr07-test' -> application 'cr07-throwaway' -> docker image hello-world:latest, deployed as a real Swarm service (docker service ls confirmed), deployment status 'done', then deleted via API (application.delete + project.remove). | G11: 10 | H11: =IF(E11="Done",G11,IF(E11="Partial",G11*0.5,0)) | I11: Platform/SRE | J11: Exercised via Dokploy's tRPC API directly (project.create -> application.create -> saveDockerProvider -> deploy), not Hermes's own terminal tool (which runs in an ephemeral sandboxed container with no docker access - confirmed during CR-08 attempt). Cleaned up immediately after confirming.
A12: CR-08 | B12: Hermes-hosted web presence | C12: Hermes deploys and serves a web page it built itself — the literal 'agent can host a web page' capability from ARCHITECTURE.md. | D12: Hermes-VPS | E12: Not Started | G12: 10 | H12: =IF(E12="Done",G12,IF(E12="Partial",G12*0.5,0)) | I12: Hermes Design Specialist
A13: CR-09 | B13: hermes-vps registered in catalog hosts/services tables | C13: Currently only described in free-text entities + ARCHITECTURE.md — no structured row, so infra tooling has zero visibility into VPS state. | D13: Hermes-VPS | E13: Done | F13: catalog host id 7 (hermes-vps) + 5 service rows (hermes-gateway, complexity-router, Caddy, Dokploy, WireGuard wg0) added 2026-10-06 | G13: 8 | H13: =IF(E13="Done",G13,IF(E13="Partial",G13*0.5,0)) | I13: Platform/SRE | J13: Registered via PostgREST. Dokploy service row notes CR-06 as the remaining gap (admin credential not recoverable from docker env/logs).
A14: CR-10 | B14: OS/package patch cadence defined | C14: No documented policy for when/how the VPS gets security patches. | D14: Hermes-VPS | E14: Done | F14: systemctl is-enabled unattended-upgrades = enabled; /etc/apt/apt.conf.d/20auto-upgrades has Update-Package-Lists=1, Unattended-Upgrade=1 | G14: 5 | H14: =IF(E14="Done",G14,IF(E14="Partial",G14*0.5,0)) | I14: Platform/SRE | J14: Already active on the Vultr image by default - verified 2026-10-06, not something that needed building.
A15: CR-11 | B15: hermes-agent version pin + upgrade process | C15: What triggers an upgrade, how it's tested before cutover. | D15: Hermes-VPS | E15: Done | F15: policy logged to catalog 2026-10-06 | G15: 5 | H15: =IF(E15="Done",G15,IF(E15="Partial",G15*0.5,0)) | I15: Platform/SRE | J15: POLICY: upgrade is manual, triggered only when a specific needed fix/feature requires it (not merely 'commits behind'). After hermes update: re-run hermes doctor + hermes security audit, confirm hermes-gateway and complexity-router still active, before considering the upgrade final.
A16: CR-12 | B16: Resource headroom monitored | C16: 4GB RAM is tight once more MCP servers/venvs stack up — needs a ceiling check, not just hope. | D16: Hermes-VPS | E16: Done | F16: hermes-memcheck.timer + .service (systemd, every 15min, logs via logger if available memory <500MB). Current baseline 2026-10-06: 257MB free / 1.7GB available of 3.8GB total, 600MB already in swap. | G16: 5 | H16: =IF(E16="Done",G16,IF(E16="Partial",G16*0.5,0)) | I16: Platform/SRE | J16: Lightweight ceiling check, not full alerting (that's OB-02's job - cross-referenced). Headroom is confirmed genuinely tight, not hypothetical.
A17: CR-13 | B17: config.yaml edits via comment-preserving method | C17: A prior full parse+dump via PyYAML silently stripped all comments; switch to ruamel.yaml or targeted text edits. Found 2026-10-05: dashboard has a form-based Config editor (150+ fields, export/import JSON) -- may sidestep the comment-stripping problem entirely since it's not a full YAML parse+dump. Untested whether it preserves comments on fields it doesn't touch. See D6_Web_Dashboard. | D17: Hermes-VPS | E17: Done | F17: hermes config set/get used exclusively throughout 2026-10-05/06 session (CR-17, SH-04, security.protected_instruction_files toggle) - never a raw PyYAML parse+dump | G17: 3 | H17: =IF(E17="Done",G17,IF(E17="Partial",G17*0.5,0)) | I17: Platform/SRE | J17: Confirmed in practice: hermes's own config CLI is the safe method, sidesteps the comment-stripping incident entirely since it's not a full-file parse+rewrite.
A18: CR-14 | B18: Staged config changes | C18: A way to validate a config.yaml change before it hits the live gateway (even a dry-run diff), so a bad edit doesn't take down the running agent. Found 2026-10-05: Checkpoints feature auto-snapshots before file writes (shadow git repo) and the Config page has reset-to-defaults/export-JSON -- may partly cover 'validate before it hits the live gateway' without custom tooling. See D6_Web_Dashboard. | D18: Hermes-VPS | E18: Done | F18: hermes checkpoints status confirmed real: shadow git repo auto-snapshots before write_file/patch/terminal calls (/home/hermes/.hermes/checkpoints) | G18: 5 | H18: =IF(E18="Done",G18,IF(E18="Partial",G18*0.5,0)) | I18: Hermes Design Specialist | J18: Built-in mechanism satisfies this without custom tooling, per the D6_Web_Dashboard lead. hermes checkpoints list/status/prune available for recovery.
A19: CR-15 | B19: Sister's Hermes — separate VPS provisioned | C19: Decided 2026-10-04: full separation, not a restricted-user account on this instance, so memory/context never bleeds between the two. Vultr High Performance AMD, 1 vCPU / 2GB RAM / 50GB NVMe, $12/mo, HermesAgent marketplace image — same pattern as hermes-vps. | D19: Hermes-VPS | E19: Not Started | F19: hermes-sister-separate-agent-2026-10-04 | G19: 8 | H19: =IF(E19="Done",G19,IF(E19="Partial",G19*0.5,0)) | I19: Product Owner (Mark) | J19: DEFERRED 2026-10-06 per explicit user decision: Sister's Hermes is put off until this Hermes instance is complete. Not abandoned, intentionally sequenced after this project's own finish line.
A20: CR-16 | B20: Sister's Hermes — local-model access decided | C20: Open question from the planning conversation: does her instance get access to w_workstation's local model, or stay Codex/cloud-only? One RTX A4000 can't serve two simultaneous agents without one waiting on the other. | D20: Either / Bridge | E20: Not Started | G20: 3 | H20: =IF(E20="Done",G20,IF(E20="Partial",G20*0.5,0)) | I20: Product Owner (Mark) | J20: DEFERRED 2026-10-06 per explicit user decision: Sister's Hermes is put off until this Hermes instance is complete. Not abandoned, intentionally sequenced after this project's own finish line.
A21: CR-17 | B21: Terminal backend: Docker — locked in | C21: LOCKED 2026-10-04: terminal.backend=docker, not local. Directly relevant to HN-05/SH-02 (gateway shell exposure) — switching off 'local' sandboxes every command Hermes runs in a container instead of executing directly on the VPS, containing blast radius even before the allowlist fix lands. Docker's already installed on hermes-vps for Dokploy. | D21: Hermes-VPS | E21: Done | F21: config.yaml: terminal.backend=docker, terminal.container_memory=1024 (box is 3.8GiB total); hermes user added to docker group, gateway restarted, 'hermes doctor' confirms Docker (daemon running) | G21: 8 | H21: =IF(E21="Done",G21,IF(E21="Partial",G21*0.5,0)) | I21: Security Reviewer | J21: APPLIED 2026-10-05: set terminal.backend=docker and terminal.container_memory=1024 (down from the 5120 default that exceeded the box's 4GB RAM). hermes doctor flagged Docker as unreachable after the config change -- root cause was the hermes user not being in the docker group (permission denied on /var/run/docker.sock). Fixed with usermod -aG docker hermes + systemctl restart hermes-gateway to pick up the new group membership. Re-ran hermes doctor: Docker (daemon running) now green.
A22: CR-18 | B22: SSH access to hermes-vps catalogued for execution | C22: DECIDED 2026-10-05: user chose to give Claude Code real SSH access (over the SSH access option) rather than routing execution through the web dashboard's Chat. No SSH credential exists in the vault yet -- hermes-vps was also confirmed absent from the catalog hosts table entirely (CR-09). Needed: host/IP, port, username, key or password. | D22: Hermes-VPS | E22: Done | F22: vault secret hermes-vps-ssh (root@207.148.2.224, same key as default ~/.ssh/id_ed25519) | G22: 5 | H22: =IF(E22="Done",G22,IF(E22="Partial",G22*0.5,0)) | I22: Platform/SRE | J22: Vaulted 2026-10-05 before any execution work began. SSH tested and used continuously since.
H23: =IF(E22="Done",G22,IF(E22="Partial",G22*0.5,0))
H24: =IF(E23="Done",G23,IF(E23="Partial",G23*0.5,0))
H25: =IF(E24="Done",G24,IF(E24="Partial",G24*0.5,0))
H26: =IF(E25="Done",G25,IF(E25="Partial",G25*0.5,0))
H27: =IF(E26="Done",G26,IF(E26="Partial",G26*0.5,0))
H28: =IF(E27="Done",G27,IF(E27="Partial",G27*0.5,0))
H29: =IF(E28="Done",G28,IF(E28="Partial",G28*0.5,0))
H30: =IF(E29="Done",G29,IF(E29="Partial",G29*0.5,0))
H31: =IF(E30="Done",G30,IF(E30="Partial",G30*0.5,0))
H32: =IF(E31="Done",G31,IF(E31="Partial",G31*0.5,0))
H33: =IF(E32="Done",G32,IF(E32="Partial",G32*0.5,0))
H34: =IF(E33="Done",G33,IF(E33="Partial",G33*0.5,0))
... H52: =IF(E51="Done",G51,IF(E51="Partial",G51*0.5,0))
B54: TAB TOTAL (includes blank headroom rows above for future additions) | G54: =SUM(G5:G51) | H54: =SUM(H5:H51) | I54: =IFERROR(TEXT(H53/G53,"0%")&" complete","0% complete")

Sheet 02_Identity_Memory
A1: Identity & Memory Continuity
A2: The thing that makes 'Hermes away from home' the same Hermes as 'at home.'
A4: ID | B4: Feature | C4: Description (execution level) | D4: Must Live On | E4: Status | F4: Evidence / Location | G4: Points | H4: Points Earned | I4: Owner Role | J4: Notes / Next Action
A5: IM-01 | B5: SOUL.md committed to hermes-vps | C5: CORRECTION 2026-10-04: an earlier pass here wrongly claimed SOUL.md wasn't real — it is, and it's distinct from MEMORY.md (see IM-09). Lives at ~/.hermes/SOUL.md, 2,200-char cap, defines WHO the agent is — persona, tone, values, boundaries, judgment style. First slot in the system prompt. Auto-created with a generic default if missing; the version drafted in conversation was never actually written to the box. | D5: Hermes-VPS | E5: Done | F5: ~/.hermes/SOUL.md (1660 bytes), confirmed correct path by hermes doctor: '✓ SOUL.md exists (persona configured)' | G5: 10 | H5: =IF(E5="Done",G5,IF(E5="Partial",G5*0.5,0)) | I5: Hermes Design Specialist | J5: Path confirmed correct via doctor source (doctor_state.py: soul_path = hermes_home / 'SOUL.md', top-level).
A6: IM-02 | B6: USER.md committed to hermes-vps | C6: User profile/preferences, 1,375-char cap, distinct from both SOUL.md and MEMORY.md. Same status — drafted, never committed. | D6: Hermes-VPS | E6: Done | F6: ~/.hermes/memories/USER.md (1036 bytes, general-only now) + separate 'Prograder Price Changes' hermes project (p_9d13c5a9, /home/hermes/prograder-price-changes/NOTES.md) holding the project-specific fact that was previously mixed into USER.md | G6: 10 | H6: =IF(E6="Done",G6,IF(E6="Partial",G6*0.5,0)) | I6: Hermes Design Specialist | J6: PRINCIPLE established 2026-10-06 per user: general files (SOUL/USER/MEMORY) are about Hermes in general, never project-specific. Found project-specific content (Prograder price-change work preferences) mixed into USER.md - created a proper hermes project for it and moved the fact there, left only general facts in USER.md.
A7: IM-03 | B7: Single conversation/session store confirmed | C7: Unverified whether every interface reads/writes one store or each starts disconnected. | D7: Hermes-VPS | E7: Not Started | G7: 10 | H7: =IF(E7="Done",G7,IF(E7="Partial",G7*0.5,0)) | I7: Hermes Design Specialist | J7: Decides whether G6 is even architecturally possible
A8: IM-04 | B8: Cross-interface continuity proven | C8: Web UI, Hermes Desktop, and (eventually) Telegram all resume the same memory, not three separate Hermeses. | D8: Hermes-VPS | E8: Not Started | G8: 10 | H8: =IF(E8="Done",G8,IF(E8="Partial",G8*0.5,0)) | I8: Hermes Design Specialist | J8: Found 2026-10-05: practical template ready -- 4 sections (Soul/Voice/Operations/Restrictions), 50-80 lines (~400-800 tokens/turn), official starter pattern available. hermes prompt-size shows actual token cost once written. This was the main blocker on this row -- ready to draft and commit. See D8_Advanced_Reference.
A9: IM-05 | B9: Extended memory provider: Hindsight — locked in | C9: LOCKED 2026-10-04, number CORRECTED 2026-10-05: after comparing all 8 official Hermes memory plugins (Hindsight, ByteRover, Supermemory, Mem0, Honcho, OpenViking, Holographic, RetainDB) plus Mnemosyne, Hindsight had the best independently-reproduced LongMemEval result. The '94.6%' originally cited here was a misread of one sub-metric (single-session-assistant) off the vectorize-io/hindsight-benchmarks leaderboard — Hindsight's actual overall LongMemEval score is 91.4% (Gemini-3 variant) / 89.0% (OSS-120B). Checked against Mastra Observational Memory's 94.87% counter-claim (which would outrank it): Mastra's number is vendor-self-reported on their own site, not independently reproduced, so it doesn't clear the same bar ByteRover's LoCoMo number was already rejected for -- decision stands, only the cited figure was wrong. Its reflect operation also directly matches the actual requirement: broad scope ('anything is fair game,' Hermes = main AI tool going forward) but genuinely curated ('remembering everything means remembering nothing') -- reflect reasons across all stored memories to produce one synthesized answer, not a ranked dump; retain does entity resolution so facts link to canonical people/projects. Local Docker mode, own Postgres, no cloud dependency -- could share a database with the migrated catalog/vault (SV-15). | D9: Hermes-VPS | E9: Partial | F9: hermes-hindsight-benchmark-correction-2026-10-05 | G9: 8 | H9: =IF(E9="Done",G9,IF(E9="Partial",G9*0.5,0)) | I9: Hermes Design Specialist | J9: Decided, not yet deployed. Depends on SV-15 landing first for the shared-database option Found 2026-10-05 (see D4_Crons_System): cron-run sessions pass skip_memory=True -- Hindsight will NOT see or inform cron job output unless that changes. Not a blocker, just dont assume cron jobs get interactive-chat memory context.
A10: IM-06 | B10: Hermes runtime-memory backup | C10: Parallel to export_catalog_memory.py, but for whatever Hermes itself remembers once IM-03 exists. | D10: Hermes-VPS | E10: Not Started | G10: 5 | H10: =IF(E10="Done",G10,IF(E10="Partial",G10*0.5,0)) | I10: Platform/SRE
A11: IM-07 | B11: Memory retention/privacy policy | C11: The built-in system already has a real policy, found 2026-10-04: facts/corrections persisted aggressively, preferences/skills only once they prove themselves, nothing sensitive ever. Capture is agent-judged, not automatic — periodic self-prompts ask 'should I persist this?' (solves humans forgetting to flag what matters). Still undefined: what the SAME policy should be for an extended provider (IM-05) once it exists, which has no built-in character cap forcing curation the way MEMORY.md's 2,200-char limit does. | D11: N/A (process/doc) | E11: Partial | F11: hermes-agent docs: persistent memory | G11: 3 | H11: =IF(E11="Done",G11,IF(E11="Partial",G11*0.5,0)) | I11: Hermes Design Specialist
A12: IM-08 | B12: Identity consistency test | C12: Ask 'who are you' from two different interfaces/locations, confirm identical answer, as an actual verification step not an assumption. | D12: N/A (process/doc) | E12: Not Started | G12: 5 | H12: =IF(E12="Done",G12,IF(E12="Partial",G12*0.5,0)) | I12: Hermes Design Specialist
A13: IM-09 | B13: MEMORY.md committed to hermes-vps | C13: Distinct from SOUL.md (IM-01): MEMORY.md holds WHAT the agent has learned — environment facts, conventions, discovered workarounds — not who it is. Same 2,200-char cap; on overflow the agent must consolidate/remove entries before adding more (some nuance gets lost in that process). Human-prunable by hand-editing the file directly; hermes memory compress --older-than 30d also exists for session-level compression. | D13: Hermes-VPS | E13: Not Started | F13: ~/.hermes/memories/MEMORY.md does not exist yet - confirmed via hermes doctor: 'MEMORY.md not created yet (will be created when the agent first writes a memory)' | G13: 8 | H13: =IF(E13="Done",G13,IF(E13="Partial",G13*0.5,0)) | I13: Hermes Design Specialist | J13: CORRECTED 2026-10-06: this is NOT a static file to hand-author - it's populated by the agent itself as it learns facts during real use (same mechanism as memories/USER.md, which already has real entries). My earlier hand-written MEMORY.md went to the wrong path AND the wrong model (static doc vs agent-grown store) - removed. Closes naturally once Hermes is actually used, not by seeding it manually.
H14: =IF(E14="Done",G14,IF(E14="Partial",G14*0.5,0))
H15: =IF(E15="Done",G15,IF(E15="Partial",G15*0.5,0))
H16: =IF(E16="Done",G16,IF(E16="Partial",G16*0.5,0))
H17: =IF(E17="Done",G17,IF(E17="Partial",G17*0.5,0))
H18: =IF(E18="Done",G18,IF(E18="Partial",G18*0.5,0))
H19: =IF(E19="Done",G19,IF(E19="Partial",G19*0.5,0))
H20: =IF(E20="Done",G20,IF(E20="Partial",G20*0.5,0))
H21: =IF(E21="Done",G21,IF(E21="Partial",G21*0.5,0))
H22: =IF(E22="Done",G22,IF(E22="Partial",G22*0.5,0))
H23: =IF(E23="Done",G23,IF(E23="Partial",G23*0.5,0))
H24: =IF(E24="Done",G24,IF(E24="Partial",G24*0.5,0))
H25: =IF(E25="Done",G25,IF(E25="Partial",G25*0.5,0))
... H43: =IF(E43="Done",G43,IF(E43="Partial",G43*0.5,0))
B45: TAB TOTAL (includes blank headroom rows above for future additions) | G45: =SUM(G5:G43) | H45: =SUM(H5:H43) | I45: =IFERROR(TEXT(H45/G45,"0%")&" complete","0% complete")

Sheet 03_Model_Routing_Resilience
A1: Model, Provider & Resilience
A2: Codex must be a COMPLETE Hermes on its own — local inference is an accelerant, never a dependency.
A4: ID | B4: Feature | C4: Description (execution level) | D4: Must Live On | E4: Status | F4: Evidence / Location | G4: Points | H4: Points Earned | I4: Owner Role | J4: Notes / Next Action
A5: MR-01 | B5: Codex linked via native link+code flow | C5: openai-codex / gpt-5.6-sol, via existing ChatGPT Plus — confirmed working for a real coding task. | D5: Hermes-VPS | E5: Done | F5: hermes-vps config.yaml providers | G5: 8 | H5: =IF(E5="Done",G5,IF(E5="Partial",G5*0.5,0)) | I5: Model/Routing Engineer
A6: MR-02 | B6: Judge-based local-vs-escalate routing live | C6: complexity_router.py replaced keyword heuristics with an LLM-as-judge call. | D6: Hermes-VPS | E6: Done | F6: complexity-router.service, 127.0.0.1:11500 | G6: 10 | H6: =IF(E6="Done",G6,IF(E6="Partial",G6*0.5,0)) | I6: Model/Routing Engineer
A7: MR-03 | B7: Hard gates: vision + bounded-task bypass | C7: has_image() forces local (Codex rejects image_url with HTTP 400); max_tokens<=32 bypasses the judge entirely for Smart Approvals. | D7: Hermes-VPS | E7: Done | F7: scripts/complexity_router.py | G7: 8 | H7: =IF(E7="Done",G7,IF(E7="Partial",G7*0.5,0)) | I7: Model/Routing Engineer
A8: MR-04 | B8: fallback_model escalation verified live | C8: 503 from the router correctly triggers Hermes's native fallback_model retry onto Codex. | D8: Hermes-VPS | E8: Done | F8: hermes-vps logs, 2026-09-27 verification | G8: 8 | H8: =IF(E8="Done",G8,IF(E8="Partial",G8*0.5,0)) | I8: Model/Routing Engineer
A9: MR-05 | B9: WireGuard-down fire drill (model only) | C9: Nobody has pulled the tunnel mid-conversation and confirmed Hermes still answers via Codex automatically. 'Fails open to local' on a judge timeout is not proven to hold when the underlying connection itself is down. Scoped to the model/routing path only — see 05_Secrets_Vault SV-14 for the matching gap in catalog/vault reachability. | D9: Hermes-VPS | E9: Not Started | G9: 15 | H9: =IF(E9="Done",G9,IF(E9="Partial",G9*0.5,0)) | I9: Model/Routing Engineer | J9: This is the exact guarantee the user is building toward
A10: MR-06 | B10: Health check / circuit breaker on local provider | C10: Proactively mark local down instead of relying on per-request timeout-and-retry. | D10: Hermes-VPS | E10: Not Started | G10: 10 | H10: =IF(E10="Done",G10,IF(E10="Partial",G10*0.5,0)) | I10: Model/Routing Engineer
A11: MR-07 | B11: Per-turn backend indicator | C11: Surface/log which backend (local vs Codex) actually answered each turn. | D11: Hermes-VPS | E11: Not Started | G11: 5 | H11: =IF(E11="Done",G11,IF(E11="Partial",G11*0.5,0)) | I11: Observability
A12: MR-08 | B12: Local runtime/model finalized | C12: See 07_Local_Inference — this row just tracks the routing-layer consequence of that decision. | D12: Home-Network | E12: Not Started | G12: 5 | H12: =IF(E12="Done",G12,IF(E12="Partial",G12*0.5,0)) | I12: Model/Routing Engineer
A13: MR-09 | B13: G8 criterion re-verified on new runtime | C13: Old proof (Ollama) will be stale the moment the runtime changes — must re-run 'one stays local, one escalates, both observed' after cutover. | D13: Either / Bridge | E13: Not Started | G13: 8 | H13: =IF(E13="Done",G13,IF(E13="Partial",G13*0.5,0)) | I13: Model/Routing Engineer
A14: MR-10 | B14: Codex spend ceiling / circuit breaker | C14: No cap or alert exists if Codex usage spikes — relevant once it's the sole fallback. | D14: Hermes-VPS | E14: Not Started | G14: 5 | H14: =IF(E14="Done",G14,IF(E14="Partial",G14*0.5,0)) | I14: Product Owner (Mark)
A15: MR-13 | B15: Vultr Serverless Inference fallback model: DeepSeek-V4-Flash — locked in | C15: LOCKED 2026-10-04: cheapest of the 8 pre-configured models ($0.30/M input, $1.00/M output), fast, general-purpose — right fit for a middle tier meant to be cheap overflow capacity, not a second Codex. Already pre-configured/credentialed on hermes-vps; just needs an explicit fallback_providers entry in config.yaml. | D15: Hermes-VPS | E15: Partial | F15: hermes-five-provider-choices-locked-2026-10-04 | G15: 5 | H15: =IF(E15="Done",G15,IF(E15="Partial",G15*0.5,0)) | I15: Model/Routing Engineer | J15: No three-tier routing logic exists yet (judge only knows local-vs-Codex) — this model is configured but not yet reachable by the router
A16: MR-11 | B16: Retry/backoff policy documented | C16: Transient local error vs. hard failure should not be handled identically. | D16: Hermes-VPS | E16: Not Started | G16: 3 | H16: =IF(E16="Done",G16,IF(E16="Partial",G16*0.5,0)) | I16: Model/Routing Engineer
A17: MR-12 | B17: Routing-decision log retention policy | C17: complexity_router.log exists and records every verdict, but nothing rotates or retains it deliberately. | D17: Hermes-VPS | E17: Partial | F17: /home/hermes/.hermes/logs/complexity_router.log | G17: 3 | H17: =IF(E17="Done",G17,IF(E17="Partial",G17*0.5,0)) | I17: Observability
H18: =IF(E18="Done",G18,IF(E18="Partial",G18*0.5,0))
H19: =IF(E19="Done",G19,IF(E19="Partial",G19*0.5,0))
H20: =IF(E20="Done",G20,IF(E20="Partial",G20*0.5,0))
H21: =IF(E21="Done",G21,IF(E21="Partial",G21*0.5,0))
H22: =IF(E22="Done",G22,IF(E22="Partial",G22*0.5,0))
H23: =IF(E23="Done",G23,IF(E23="Partial",G23*0.5,0))
H24: =IF(E24="Done",G24,IF(E24="Partial",G24*0.5,0))
H25: =IF(E25="Done",G25,IF(E25="Partial",G25*0.5,0))
H26: =IF(E26="Done",G26,IF(E26="Partial",G26*0.5,0))
H27: =IF(E27="Done",G27,IF(E27="Partial",G27*0.5,0))
H28: =IF(E28="Done",G28,IF(E28="Partial",G28*0.5,0))
H29: =IF(E29="Done",G29,IF(E29="Partial",G29*0.5,0))
... H47: =IF(E47="Done",G47,IF(E47="Partial",G47*0.5,0))
B49: TAB TOTAL (includes blank headroom rows above for future additions) | G49: =SUM(G5:G47) | H49: =SUM(H5:H47) | I49: =IFERROR(TEXT(H49/G49,"0%")&" complete","0% complete")

Sheet 04_Tool_MCP_Layer
A1: Tool / MCP Capability Layer
A2: Every network resource as an agent capability — and ONE deployment per capability, not one per environment.
A4: ID | B4: Feature | C4: Description (execution level) | D4: Must Live On | E4: Status | F4: Evidence / Location | G4: Points | H4: Points Earned | I4: Owner Role | J4: Notes / Next Action
A5: TM-01 | B5: catalog_mcp.py — VPS-only | C5: 6 tools (get_entities, get_hosts, get_services, add_entity, add_relation, graph_recall), isolated venv, verified live. | D5: Hermes-VPS | E5: Done | F5: /home/hermes/.hermes/mcp_servers/catalog/ | G5: 8 | H5: =IF(E5="Done",G5,IF(E5="Partial",G5*0.5,0)) | I5: Platform/SRE
A6: TM-02 | B6: search_mcp.py — VPS-only, web_search reliable | C6: Brave API-backed, verified via real hermes -z call. | D6: Hermes-VPS | E6: Done | F6: /home/hermes/.hermes/mcp_servers/search/ | G6: 8 | H6: =IF(E6="Done",G6,IF(E6="Partial",G6*0.5,0)) | I6: Platform/SRE
A7: TM-03 | B7: fetch_page tool-recognition fixed | C7: Model inconsistently recognizes the tool exists across invocation modes (chat -q vs -z --cli) — root cause not isolated yet. | D7: Hermes-VPS | E7: Not Started | F7: scripts/search_mcp.py — open bug | G7: 5 | H7: =IF(E7="Done",G7,IF(E7="Partial",G7*0.5,0)) | I7: Model/Routing Engineer
A8: TM-04 | B8: infra_mcp.py — Salt wrapping | C8: salt_run / salt_minion_status, auto-refreshing auth token, scoped eauth user. | D8: Hermes-VPS | E8: Done | F8: hermes-vps config.yaml mcp_servers.infra | G8: 8 | H8: =IF(E8="Done",G8,IF(E8="Partial",G8*0.5,0)) | I8: Home-Network Liaison
A9: TM-05 | B9: infra_mcp.py — MeshCentral + Beszel wrapping | C9: Original goal was a unified Salt+MeshCentral+Beszel surface; only Salt got built. | D9: Hermes-VPS | E9: Not Started | F9: scripts/infra_mcp.py | G9: 8 | H9: =IF(E9="Done",G9,IF(E9="Partial",G9*0.5,0)) | I9: Home-Network Liaison
A10: TM-06 | B10: vault_mcp.py consolidated to ONE deployment | C10: Currently 4 independent copies/venvs: hermes-vps, laptop Claude Code .mcp.json, laptop Codex config.toml, and a project-scoped .codex/config.toml. Same tool, four things to keep in sync by hand. Scored under 05_Secrets_Vault SV-12 — this row is the tooling-side cross-reference, not separately weighted. | D10: Hermes-VPS | E10: Not Started | F10: 4x — scored at SV-12 | G10: 0 | H10: =IF(E10="Done",G10,IF(E10="Partial",G10*0.5,0)) | I10: Hermes Design Specialist | J10: Decide: single VPS-only server all clients call remotely, or explicitly-temporary local copies with a documented sunset
A11: TM-07 | B11: Nous native Tool Gateway configured | C11: CORRECTED 2026-10-05: this is 4 tools only (web_search/Firecrawl, image_gen/FAL, TTS/OpenAI, browser automation/Browser Use), opt-in per-tool via use_gateway:true, requires a PAID Nous Portal subscription (not available on free tier for these 4). The earlier '5 sandboxed exec backends' description was wrong -- that's actually the terminal tool's 7 backends (local/docker/ssh/singularity/modal/daytona/vercel_sandbox), a separate system already covered by CR-17. See D8_Advanced_Reference. | D11: Hermes-VPS | E11: Not Started | G11: 8 | H11: =IF(E11="Done",G11,IF(E11="Partial",G11*0.5,0)) | I11: Platform/SRE | J11: Given Obscura + existing web-search/TTS providers already locked in, likely not worth a paid Portal subscription just for this.
A12: TM-08 | B12: Remote-desktop capability fully enrolled | C12: MeshCentral (had zero devices connected since July) was replaced by Apache Guacamole 2026-10-01 — RDP/SSH native, no agents needed. w_workstation proven end-to-end; other hosts not yet confirmed through it. | D12: Home-Network | E12: Partial | F12: guacamole-deployed-fileserver-2026-10-01 | G12: 5 | H12: =IF(E12="Done",G12,IF(E12="Partial",G12*0.5,0)) | I12: Home-Network Liaison
A13: TM-09 | B13: Unified admin surface for mixed local ecosystem | C13: Open user ask (2026-09-30): broader than Salt alone, MCP-accessible. | D13: Home-Network | E13: Not Started | G13: 8 | H13: =IF(E13="Done",G13,IF(E13="Partial",G13*0.5,0)) | I13: Home-Network Liaison
A14: TM-10 | B14: Playbook: promote a home capability to a Hermes tool | C14: A repeatable, documented process — not ad hoc each time. | D14: N/A (process/doc) | E14: Not Started | G14: 5 | H14: =IF(E14="Done",G14,IF(E14="Partial",G14*0.5,0)) | I14: Hermes Design Specialist
A15: TM-11 | B15: Least-privilege review across all MCP credentials | C15: salt-hermes-infra is properly scoped (no wheel/runner); others not reviewed the same way. | D15: Either / Bridge | E15: Partial | G15: 5 | H15: =IF(E15="Done",G15,IF(E15="Partial",G15*0.5,0)) | I15: Security Reviewer
A16: TM-12 | B16: MCP server dependency/version pinning | C16: FastMCP version and venv contents should be reproducible, not whatever was latest at deploy time. | D16: Hermes-VPS | E16: Not Started | G16: 3 | H16: =IF(E16="Done",G16,IF(E16="Partial",G16*0.5,0)) | I16: Platform/SRE
A17: TM-13 | B17: Tool-call audit trail | C17: No record of who/what invoked which tool, when — matters once multiple agents (Hermes, Claude Code, Codex) share the same tool surface. | D17: Hermes-VPS | E17: Not Started | G17: 5 | H17: =IF(E17="Done",G17,IF(E17="Partial",G17*0.5,0)) | I17: Security Reviewer
A18: TM-14 | B18: Browser automation: Obscura — locked in | C18: LOCKED 2026-10-04: Obscura (Rust headless browser, ~30MB/instance) over local Chrome/Camofox (200-400MB+/instance — too heavy for a 4GB VPS already running several services) and cloud options (Browserbase/Browser Use, paid). Known risk, stated plainly: NOT officially supported by hermes-agent core — the integration request was closed as not planned. Only available via the community plugin hermes-plugin-obscura. | D18: Hermes-VPS | E18: Partial | F18: hermes-browser-automation-obscura-2026-10-04 | G18: 5 | H18: =IF(E18="Done",G18,IF(E18="Partial",G18*0.5,0)) | I18: Hermes Design Specialist | J18: Install: hermes plugins install SGavrl/hermes-plugin-obscura --enable. Unofficial-plugin risk accepted knowingly, not overlooked
H19: =IF(E19="Done",G19,IF(E19="Partial",G19*0.5,0))
H20: =IF(E20="Done",G20,IF(E20="Partial",G20*0.5,0))
H21: =IF(E21="Done",G21,IF(E21="Partial",G21*0.5,0))
H22: =IF(E22="Done",G22,IF(E22="Partial",G22*0.5,0))
H23: =IF(E23="Done",G23,IF(E23="Partial",G23*0.5,0))
H24: =IF(E24="Done",G24,IF(E24="Partial",G24*0.5,0))
H25: =IF(E25="Done",G25,IF(E25="Partial",G25*0.5,0))
H26: =IF(E26="Done",G26,IF(E26="Partial",G26*0.5,0))
H27: =IF(E27="Done",G27,IF(E27="Partial",G27*0.5,0))
H28: =IF(E28="Done",G28,IF(E28="Partial",G28*0.5,0))
H29: =IF(E29="Done",G29,IF(E29="Partial",G29*0.5,0))
H30: =IF(E30="Done",G30,IF(E30="Partial",G30*0.5,0))
... H48: =IF(E48="Done",G48,IF(E48="Partial",G48*0.5,0))
B50: TAB TOTAL (includes blank headroom rows above for future additions) | G50: =SUM(G5:G48) | H50: =SUM(H5:H48) | I50: =IFERROR(TEXT(H50/G50,"0%")&" complete","0% complete")

Sheet 05_Secrets_Vault
A1: Secrets & Vault
A2: If a tool needs a password, it comes from here at call time — never hardcoded, never duplicated at rest.
A4: ID | B4: Feature | C4: Description (execution level) | D4: Must Live On | E4: Status | F4: Evidence / Location | G4: Points | H4: Points Earned | I4: Owner Role | J4: Notes / Next Action
A5: SV-01 | B5: Vault backing store live | C5: Postgres secrets table, pgcrypto-encrypted, secret_get/secret_set RPCs, passcode supplied per-call only. Backing store physically lives on fileserver (Home-Network), reached by hermes-vps over the WireGuard tunnel — see SV-14 for why that matters. | D5: Home-Network | E5: Done | F5: fileserver:3003 catalog-db | G5: 8 | H5: =IF(E5="Done",G5,IF(E5="Partial",G5*0.5,0)) | I5: Secrets Custodian | J5: CLARIFIED 2026-10-05: this row is about the EXTERNAL catalog Postgres vault (pgp_sym_encrypt). Hermes ALSO has its own separate, local, Fernet-encrypted Credential Vault (~/.hermes/vault/, for browser-fill passwords) plus a distinct Credential Pools feature (multi-key rotation per provider) and an 'API Keys' dashboard page (.env management, not encrypted at rest). Four different 'vault-shaped' things now exist -- don't conflate them. See D6_Web_Dashboard.
A6: SV-02 | B6: 10 secrets migrated | C6: w_workstation-llm, w_workstation-mguy, server-mark-sudo, server-portainer-admin, hermes-vps-caddy-basic-auth, hermes-vps-dashboard-basic-auth, hermes-vps-vultr-inference-api-key, hermes-vps-brave-search-api-key, meshcentral-claude-login-token, salt-hermes-infra. | D6: Either / Bridge | E6: Done | F6: vault | G6: 10 | H6: =IF(E6="Done",G6,IF(E6="Partial",G6*0.5,0)) | I6: Secrets Custodian
A7: SV-03 | B7: DuckDNS token in vault | C7: Not yet migrated. | D7: Home-Network | E7: Not Started | G7: 3 | H7: =IF(E7="Done",G7,IF(E7="Partial",G7*0.5,0)) | I7: Secrets Custodian
A8: SV-04 | B8: NPM admin login in vault | C8: Not yet migrated. | D8: Home-Network | E8: Not Started | G8: 3 | H8: =IF(E8="Done",G8,IF(E8="Partial",G8*0.5,0)) | I8: Secrets Custodian
A9: SV-05 | B9: WordPress / MariaDB creds in vault | C9: Not yet migrated. | D9: Home-Network | E9: Not Started | G9: 3 | H9: =IF(E9="Done",G9,IF(E9="Partial",G9*0.5,0)) | I9: Secrets Custodian
A10: SV-06 | B10: AdGuard admin in vault | C10: Not yet migrated. | D10: Home-Network | E10: Not Started | G10: 3 | H10: =IF(E10="Done",G10,IF(E10="Partial",G10*0.5,0)) | I10: Secrets Custodian
A11: SV-07 | B11: Modal API key located + vaulted | C11: Location not even fully confirmed yet, separate from being in the vault. | D11: Hermes-VPS | E11: Not Started | G11: 5 | H11: =IF(E11="Done",G11,IF(E11="Partial",G11*0.5,0)) | I11: Secrets Custodian
A12: SV-08 | B12: /Dockers share plaintext .env exposure remediated | C12: Every container's real secrets (DB passwords, Portainer admin) sit on an anonymous guest-accessible SMB share, by deliberate design choice — the single largest exposure on the network and outside the vault effort entirely. | D12: Home-Network | E12: Not Started | F12: server:/Dockers (guest ok=yes) | G12: 15 | H12: =IF(E12="Done",G12,IF(E12="Partial",G12*0.5,0)) | I12: Security Reviewer | J12: Biggest single item on this whole workbook. Scored here; see 12_Security_Hardening SH-03 cross-reference
A13: SV-09 | B13: Vultr inference key removed from config.yaml plaintext | C13: In the vault now, but never confirmed the plaintext copy in providers.vultr was actually deleted rather than just duplicated. | D13: Hermes-VPS | E13: Not Started | F13: hermes-vps config.yaml | G13: 3 | H13: =IF(E13="Done",G13,IF(E13="Partial",G13*0.5,0)) | I13: Secrets Custodian
A14: SV-10 | B14: Secret rotation policy | C14: Nothing defines when/how any of the 10 vaulted secrets get rotated. | D14: N/A (process/doc) | E14: Not Started | G14: 5 | H14: =IF(E14="Done",G14,IF(E14="Partial",G14*0.5,0)) | I14: Secrets Custodian
A15: SV-11 | B15: Vault access audit log | C15: No record of who called get_secret, when, for what. | D15: Hermes-VPS | E15: Not Started | G15: 5 | H15: =IF(E15="Done",G15,IF(E15="Partial",G15*0.5,0)) | I15: Security Reviewer
A16: SV-12 | B16: Vault server consolidated to one deployment | C16: Same underlying item as 04_Tool_MCP_Layer TM-06 — scored here since it's fundamentally a secrets-handling problem, not just a tooling one. | D16: Hermes-VPS | E16: Not Started | F16: 4x deployments | G16: 12 | H16: =IF(E16="Done",G16,IF(E16="Partial",G16*0.5,0)) | I16: Hermes Design Specialist
A17: SV-14 | B17: Catalog/vault reachability defined for tunnel-down | C17: catalog_mcp.py and vault_mcp.py on hermes-vps both call out to fileserver:3003 over the WireGuard tunnel. 03_Model_Routing_Resilience's MR-05 fire drill only covers the local model falling back to Codex — it does NOT cover what happens to Hermes's memory and secrets access if the same tunnel is down. SUPERSEDED by the 2026-10-04 VPS self-sufficiency rule: the answer isn't 'define acceptable degradation,' it's 'this dependency on the home network isn't allowed to exist' — see SV-15. | D17: Either / Bridge | E17: Not Started | G17: 12 | H17: =IF(E17="Done",G17,IF(E17="Partial",G17*0.5,0)) | I17: Hermes Design Specialist | J17: Resolved in principle by SV-15; this row closes once that migration lands
A18: SV-15 | B18: Catalog + vault migrated off fileserver | C18: Required by the 2026-10-04 VPS self-sufficiency rule: hermes-vps must be able to do everything except run the local LLM without depending on the home network. Catalog + vault currently live on fileserver, which violates this. Target: Vultr Managed Database (Postgres, supports pgvector for free) — also solves IM-05's memory-provider storage need in the same move. | D18: Hermes-VPS | E18: Not Started | F18: hermes-catalog-vault-migration-required-2026-10-04 | G18: 12 | H18: =IF(E18="Done",G18,IF(E18="Partial",G18*0.5,0)) | I18: Hermes Design Specialist | J18: Closes SV-14 entirely once done; also unblocks IM-05's Hindsight shared-database option
A19: SV-13 | B19: Human-side passcode storage policy | C19: Define how the vault/Salt passcode is stored and retrieved on the human side (e.g. a password manager entry) so it never needs to be typed into a chat session. | D19: N/A (process/doc) | E19: Not Started | G19: 5 | H19: =IF(E19="Done",G19,IF(E19="Partial",G19*0.5,0)) | I19: Product Owner (Mark) | J19: Passcode was typed directly in chat on 2026-10-03; not persisted anywhere by Claude, but this feature would make that unnecessary going forward
A20: SV-16 | B20: Hermes native Credential Vault + Credential Pools -- reviewed, not adopted | C20: Found 2026-10-05: Hermes ships its own local browser-password vault (~/.hermes/vault/, Fernet-encrypted, distinct from the catalog vault above) and a Credential Pools feature (multiple API keys per provider, auto-rotation on rate-limit). Neither currently used. Pools could add resilience to Anthropic/OpenRouter calls cheaply if ever rate-limited; native Vault is the natural home for any login credentials TM-14's Obscura browser automation needs to fill. | D20: Hermes-VPS | E20: Not Started | F20: hermes-web-dashboard-survey-2026-10-05 | G20: 3 | H20: =IF(E20="Done",G20,IF(E20="Partial",G20*0.5,0)) | I20: Hermes Design Specialist | J20: No action needed yet -- noting the capability exists for when Obscura or rate-limiting makes it relevant Found 2026-10-05: hermes egress (iron-proxy) composes with Bitwarden Secrets Manager specifically for sandbox credential protection (opaque proxy tokens, Docker-backend only, matches CR-17). OPEN QUESTION, not resolved: does it require Bitwarden specifically, or can it pull from the existing catalog vault instead? Don't adopt Bitwarden as a new system without checking this first. See D8_Advanced_Reference.
H21: =IF(E21="Done",G21,IF(E21="Partial",G21*0.5,0))
H22: =IF(E22="Done",G22,IF(E22="Partial",G22*0.5,0))
H23: =IF(E23="Done",G23,IF(E23="Partial",G23*0.5,0))
H24: =IF(E24="Done",G24,IF(E24="Partial",G24*0.5,0))
H25: =IF(E25="Done",G25,IF(E25="Partial",G25*0.5,0))
H26: =IF(E26="Done",G26,IF(E26="Partial",G26*0.5,0))
H27: =IF(E27="Done",G27,IF(E27="Partial",G27*0.5,0))
H28: =IF(E28="Done",G28,IF(E28="Partial",G28*0.5,0))
H29: =IF(E29="Done",G29,IF(E29="Partial",G29*0.5,0))
H30: =IF(E30="Done",G30,IF(E30="Partial",G30*0.5,0))
H31: =IF(E31="Done",G31,IF(E31="Partial",G31*0.5,0))
H32: =IF(E32="Done",G32,IF(E32="Partial",G32*0.5,0))
... H49: =IF(E49="Done",G49,IF(E49="Partial",G49*0.5,0))
B51: TAB TOTAL (includes blank headroom rows above for future additions) | G51: =SUM(G5:G49) | H51: =SUM(H5:H49) | I51: =IFERROR(TEXT(H51/G51,"0%")&" complete","0% complete")

Sheet 06_Home_Network_Boundary
A1: Home-Network Capability Boundary
A2: The home network is a swappable capability PROVIDER, reached over WireGuard. It is never where Hermes lives.
A4: ID | B4: Feature | C4: Description (execution level) | D4: Must Live On | E4: Status | F4: Evidence / Location | G4: Points | H4: Points Earned | I4: Owner Role | J4: Notes / Next Action
A5: HN-01 | B5: WireGuard tunnel live, subnet routing confirmed | C5: 10.60.0.0/24, VPS 10.60.0.1 / home 10.60.0.2 on fileserver, verified ping + API reachability end-to-end. | D5: Home-Network | E5: Done | F5: fileserver WireGuard container | G5: 10 | H5: =IF(E5="Done",G5,IF(E5="Partial",G5*0.5,0)) | I5: Home-Network Liaison
A6: HN-02 | B6: IP forwarding + NAT + FORWARD rules | C6: net.ipv4.ip_forward=1, explicit ACCEPT persisted in PostUp/PostDown. | D6: Home-Network | E6: Done | F6: fileserver | G6: 5 | H6: =IF(E6="Done",G6,IF(E6="Partial",G6*0.5,0)) | I6: Home-Network Liaison
A7: HN-03 | B7: Home-network capability scope documented in one place | C7: Two same-day 2026-09-23 decisions define this: web/Docker presence moved to the VPS specifically to avoid exposing home ports, AND the VPN was explicitly scoped to also carry Salt (not just the local model) — both were deliberate, not sequential scope creep. Worth writing down as one coherent statement instead of two separate catalog entities a reader has to reconcile. | D7: N/A (process/doc) | E7: Not Started | F7: hermes-web-and-docker-presence-shifts-to-vps-2026-09-23, hermes-vpn-scope-includes-salt-2026-09-23 | G7: 5 | H7: =IF(E7="Done",G7,IF(E7="Partial",G7*0.5,0)) | I7: Hermes Design Specialist
A8: HN-04 | B8: Device-management capability, current state documented | C8: MeshCentral (the original device-mgmt pick) was fully replaced by Apache Guacamole 2026-10-01 — RDP/SSH native, no agent install needed, proven end-to-end for w_workstation. This row now just needs the remaining hosts (w_desktop, fileserver, server) confirmed through Guacamole too. | D8: Home-Network | E8: Partial | F8: guacamole-deployed-fileserver-2026-10-01 | G8: 5 | H8: =IF(E8="Done",G8,IF(E8="Partial",G8*0.5,0)) | I8: Home-Network Liaison
A9: HN-05 | B9: Gateway arbitrary-shell exposure closed | C9: GATEWAY_ALLOW_ALL_USERS=true + 0.0.0.0 + local terminal backend = unauthenticated shell access over the tunnel/LAN. Hermes's own docs warn against this combination. | D9: Hermes-VPS | E9: Not Started | F9: hermes-vps config.yaml | G9: 15 | H9: =IF(E9="Done",G9,IF(E9="Partial",G9*0.5,0)) | I9: Security Reviewer | J9: High priority — add an allowlist or disable ALLOW_ALL_USERS. Scored here; see 12_Security_Hardening SH-02 cross-reference
A10: HN-06 | B10: Tunnel-down alerting | C10: No notification today if the WireGuard link drops — ties to MR-05's fire drill. | D10: Either / Bridge | E10: Not Started | G10: 5 | H10: =IF(E10="Done",G10,IF(E10="Partial",G10*0.5,0)) | I10: Observability
A11: HN-07 | B11: Minimum-exposure audit of tunnel ACL | C11: Confirm only catalog/Salt/LLM ports are actually reachable over the tunnel, nothing incidental. | D11: Home-Network | E11: Not Started | G11: 5 | H11: =IF(E11="Done",G11,IF(E11="Partial",G11*0.5,0)) | I11: Security Reviewer
A12: HN-08 | B12: WireGuard key rotation policy | C12: No defined cadence or trigger for rotating the tunnel keypair. | D12: Home-Network | E12: Not Started | G12: 3 | H12: =IF(E12="Done",G12,IF(E12="Partial",G12*0.5,0)) | I12: Security Reviewer
A13: HN-09 | B13: Home Assistant existence on home network -- unconfirmed | C13: Open question raised 2026-10-05 (D6/D8): a real Hermes plugin exists for Home Assistant (bigger than the Hue-only skill already found) -- but whether HA actually runs on the home network is unconfirmed. User said 'not sure' when asked directly. | D13: N/A (process/doc) | E13: Not Started | G13: 2 | H13: =IF(E13="Done",G13,IF(E13="Partial",G13*0.5,0)) | I13: Home-Network Liaison | J13: Not blocking execution -- check later, only relevant if HA turns out to exist.
H14: =IF(E13="Done",G13,IF(E13="Partial",G13*0.5,0))
H15: =IF(E14="Done",G14,IF(E14="Partial",G14*0.5,0))
H16: =IF(E15="Done",G15,IF(E15="Partial",G15*0.5,0))
H17: =IF(E16="Done",G16,IF(E16="Partial",G16*0.5,0))
H18: =IF(E17="Done",G17,IF(E17="Partial",G17*0.5,0))
H19: =IF(E18="Done",G18,IF(E18="Partial",G18*0.5,0))
H20: =IF(E19="Done",G19,IF(E19="Partial",G19*0.5,0))
H21: =IF(E20="Done",G20,IF(E20="Partial",G20*0.5,0))
H22: =IF(E21="Done",G21,IF(E21="Partial",G21*0.5,0))
H23: =IF(E22="Done",G22,IF(E22="Partial",G22*0.5,0))
H24: =IF(E23="Done",G23,IF(E23="Partial",G23*0.5,0))
H25: =IF(E24="Done",G24,IF(E24="Partial",G24*0.5,0))
... H43: =IF(E42="Done",G42,IF(E42="Partial",G42*0.5,0))
B45: TAB TOTAL (includes blank headroom rows above for future additions) | G45: =SUM(G5:G42) | H45: =SUM(H5:H42) | I45: =IFERROR(TEXT(H44/G44,"0%")&" complete","0% complete")

Sheet 07_Local_Inference
A1: Local Inference Tier
A2: The free-tier accelerant on w_workstation. Optional by definition — see 03_Model_Routing_Resilience for why it must never be load-bearing.
A4: ID | B4: Feature | C4: Description (execution level) | D4: Must Live On | E4: Status | F4: Evidence / Location | G4: Points | H4: Points Earned | I4: Owner Role | J4: Notes / Next Action
A5: LI-01 | B5: Hardware profiled via Salt | C5: Xeon W-2225 (4c/8t), 64GB RAM (2x32GB @ 2933MT/s), RTX A4000 16GB, PCIe 3.0 x16 — verified 2026-10-03. | D5: Home-Network | E5: Done | F5: w_workstation | G5: 5 | H5: =IF(E5="Done",G5,IF(E5="Partial",G5*0.5,0)) | I5: Model/Routing Engineer
A6: LI-02 | B6: Ollama excluded as target runtime | C6: User decision, 2026-10-02 — no MoE-aware expert-offload control. | D6: Home-Network | E6: Done | F6: catalog decision entity | G6: 3 | H6: =IF(E6="Done",G6,IF(E6="Partial",G6*0.5,0)) | I6: Model/Routing Engineer
A7: LI-03 | B7: Runtime chosen: ik_llama.cpp — locked in | C7: LOCKED 2026-10-04: ik_llama.cpp over vLLM and KTransformers. vLLM has no official Windows support at all (only unofficial community forks); llama.cpp/ik_llama.cpp has real native Windows builds, no WSL2 needed. ik_llama.cpp specifically exists for this use case: offloading MoE inactive experts to system RAM on consumer hardware. | D7: Home-Network | E7: Partial | F7: hermes-five-provider-choices-locked-2026-10-04 | G7: 10 | H7: =IF(E7="Done",G7,IF(E7="Partial",G7*0.5,0)) | I7: Model/Routing Engineer | J7: Decided, not yet installed/benchmarked. Build dependencies found — see D2_Providers_And_Deps
A8: LI-04 | B8: Model chosen + pulled | C8: Locked in 2026-10-04: Qwen3.6-35B-A3B. Compared against Qwen3.8-27B (dense, rejected — forfeits MoE RAM-offload), Qwen3.8-Flash-Next (MoE but ~2x oversized for this RAM/VRAM budget), and a community Qwen3.8-distilled 35B-A3B (same shape, but scored worse on real agentic tasks: 10/20 vs 16/20). Chosen, not yet pulled or benchmarked. | D8: Home-Network | E8: Partial | F8: hermes-local-model-locked-qwen3.6-35b-a3b-2026-10-04 | G8: 8 | H8: =IF(E8="Done",G8,IF(E8="Partial",G8*0.5,0)) | I8: Model/Routing Engineer | J8: Pulling + benchmarking (LI-07) is the remaining step Found 2026-10-05 (community report, see D7_Setup_Execution_Workflow): Qwen3.5-35B-A3B (one version behind this project's locked Qwen3.6-35B-A3B) reportedly defaults to curl/exec-python instead of specialized tools -- a confidence/token-efficiency heuristic in smaller local models, fixable with an explicit tool-prioritization system-prompt directive. Worth testing specifically during LI-07 benchmarking, not just raw capability. Found 2026-10-05: tool-calling requires a specific server flag or it silently fails as text (llama.cpp: --jinja; vLLM: --enable-auto-tool-choice --tool-call-parser hermes; SGLang: --tool-call-parser qwen). ik_llama.cpp's own equivalent NOT yet verified -- check before assuming tool-calling works. See D8_Advanced_Reference.
A9: LI-05 | B9: WSL2 installed (if vLLM chosen) | C9: No official vLLM Windows build — blocks LI-03 if vLLM wins. | D9: Home-Network | E9: Not Started | G9: 5 | H9: =IF(E9="Done",G9,IF(E9="Partial",G9*0.5,0)) | I9: Model/Routing Engineer
A10: LI-06 | B10: Context window aligned with Hermes's floor | C10: Hermes has a hard MINIMUM_CONTEXT_LENGTH=64_000; new provider's --max-model-len must be >=65536, matched in config.yaml (static, not live-probed). | D10: Either / Bridge | E10: Not Started | F10: agent/model_metadata.py:272 (hermes-vps) | G10: 5 | H10: =IF(E10="Done",G10,IF(E10="Partial",G10*0.5,0)) | I10: Model/Routing Engineer | J10: Found 2026-10-05: auto-detection from /v1/models is often wrong for local servers (2048 is a common failure symptom) -- set model.context_length explicitly in config.yaml. Hermes's stated floor is 64k for full feature support. This row can move to Done once that's set and verified against the real runtime. See D8_Advanced_Reference.
A11: LI-07 | B11: Benchmark vs. current 4B/8B baseline | C11: Speed + tool-call correctness head-to-head before cutover. | D11: Home-Network | E11: Not Started | G11: 8 | H11: =IF(E11="Done",G11,IF(E11="Partial",G11*0.5,0)) | I11: Model/Routing Engineer
A12: LI-08 | B12: Ollama decommissioned | C12: By design, only AFTER the replacement is verified end-to-end — brief coexistence is intentional, not a mistake. | D12: Home-Network | E12: Not Started | G12: 3 | H12: =IF(E12="Done",G12,IF(E12="Partial",G12*0.5,0)) | I12: Model/Routing Engineer
A13: LI-09 | B13: Vision capability preserved | C13: Don't lose the qwen3-vl screenshot/OCR capability when the runtime changes. | D13: Home-Network | E13: Not Started | G13: 5 | H13: =IF(E13="Done",G13,IF(E13="Partial",G13*0.5,0)) | I13: Model/Routing Engineer
A14: LI-10 | B14: Embeddings model preserved | C14: nomic-embed-text (or equivalent) needed for memory/RAG — easy to drop when swapping runtimes. | D14: Home-Network | E14: Not Started | G14: 5 | H14: =IF(E14="Done",G14,IF(E14="Partial",G14*0.5,0)) | I14: Model/Routing Engineer
A15: LI-11 | B15: GPU driver version policy | C15: No pinning/testing policy for NVIDIA driver updates on w_workstation. | D15: Home-Network | E15: Not Started | G15: 3 | H15: =IF(E15="Done",G15,IF(E15="Partial",G15*0.5,0)) | I15: Home-Network Liaison
A16: LI-12 | B16: Never-sleep power settings confirmed | C16: Flagged as an open question in VISION.md — never actually locked down. | D16: Home-Network | E16: Not Started | G16: 5 | H16: =IF(E16="Done",G16,IF(E16="Partial",G16*0.5,0)) | I16: Home-Network Liaison
H17: =IF(E17="Done",G17,IF(E17="Partial",G17*0.5,0))
H18: =IF(E18="Done",G18,IF(E18="Partial",G18*0.5,0))
H19: =IF(E19="Done",G19,IF(E19="Partial",G19*0.5,0))
H20: =IF(E20="Done",G20,IF(E20="Partial",G20*0.5,0))
H21: =IF(E21="Done",G21,IF(E21="Partial",G21*0.5,0))
H22: =IF(E22="Done",G22,IF(E22="Partial",G22*0.5,0))
H23: =IF(E23="Done",G23,IF(E23="Partial",G23*0.5,0))
H24: =IF(E24="Done",G24,IF(E24="Partial",G24*0.5,0))
H25: =IF(E25="Done",G25,IF(E25="Partial",G25*0.5,0))
H26: =IF(E26="Done",G26,IF(E26="Partial",G26*0.5,0))
H27: =IF(E27="Done",G27,IF(E27="Partial",G27*0.5,0))
H28: =IF(E28="Done",G28,IF(E28="Partial",G28*0.5,0))
... H46: =IF(E46="Done",G46,IF(E46="Partial",G46*0.5,0))
B48: TAB TOTAL (includes blank headroom rows above for future additions) | G48: =SUM(G5:G46) | H48: =SUM(H5:H46) | I48: =IFERROR(TEXT(H48/G48,"0%")&" complete","0% complete")

Sheet 08_Interfaces_Access
A1: Interfaces & Access Paths
A2: However you reach Hermes, it must be the same Hermes — this tab is about the doors, not what's behind them.
A4: ID | B4: Feature | C4: Description (execution level) | D4: Must Live On | E4: Status | F4: Evidence / Location | G4: Points | H4: Points Earned | I4: Owner Role | J4: Notes / Next Action
A5: IA-01 | B5: Web UI access path decided | C5: Password-gated, behind existing DuckDNS + NPM, path-based Custom Location on theguylab.duckdns.org. | D5: Hermes-VPS | E5: Done | F5: decision only, not yet built | G5: 3 | H5: =IF(E5="Done",G5,IF(E5="Partial",G5*0.5,0)) | I5: Interface Engineer
A6: IA-02 | B6: Web UI Custom Location + auth built | C6: Basic Auth vs. app-level login still an open decision; nothing built either way. | D6: Hermes-VPS | E6: Not Started | G6: 8 | H6: =IF(E6="Done",G6,IF(E6="Partial",G6*0.5,0)) | I6: Interface Engineer | J6: See SH-06 cross-reference and D6_Web_Dashboard -- the dashboard's own 3-tier auth model (loopback/password/OAuth/OIDC) is the mechanism this row would actually configure, not something to build custom.
A7: IA-03 | B7: Hermes Desktop installed, pointed at VPS backend | C7: Zero progress — this is G6, and blocks ever proving 'same experience, two locations.' | D7: N/A (process/doc) | E7: Not Started | G7: 10 | H7: =IF(E7="Done",G7,IF(E7="Partial",G7*0.5,0)) | I7: Interface Engineer
A8: IA-04 | B8: Same-experience-two-locations test executed | C8: The actual proof step for G6 — not built until IA-03 exists. | D8: N/A (process/doc) | E8: Not Started | G8: 5 | H8: =IF(E8="Done",G8,IF(E8="Partial",G8*0.5,0)) | I8: Hermes Design Specialist
A9: IA-05 | B9: Telegram channel configured — locked in | C9: LOCKED 2026-10-04: Telegram over Signal — official Bot API (reliable) vs. Signal's unofficial signal-cli integration (more brittle). hermes-gateway process is running; no channel wired on top of it yet. This is the interface built specifically for the GP 'looks like ordinary traffic' constraint. | D9: Hermes-VPS | E9: Partial | F9: hermes-five-provider-choices-locked-2026-10-04 | G9: 10 | H9: =IF(E9="Done",G9,IF(E9="Partial",G9*0.5,0)) | I9: Interface Engineer | J9: Needs a Telegram Bot token via BotFather — a new vault-worthy credential, not yet created Found 2026-10-05: the dashboard's Pairing page is the built-in UI for approving/revoking Telegram (and other platform) users once the bot token exists -- no custom approval flow needed. See D6_Web_Dashboard. Found 2026-10-05, exact verified sequence: hermes gateway setup (config only, doesn't start) -> hermes gateway run foreground, confirm 'telegram connected' in log -> Ctrl-C -> hermes gateway start for the managed service. Polling mode = no inbound firewall port needed. Non-interactive install: printf 'n\nY\n' | hermes gateway install. See D8_Advanced_Reference.
A10: IA-06 | B10: GP-workstation-as-backend-host / Zscaler-bypass resolved | C10: Both still-open asks point the opposite direction from the 'ordinary traffic only' design — a decision either way closes this out. | D10: N/A (process/doc) | E10: Not Started | F10: flagged, unresolved | G10: 8 | H10: =IF(E10="Done",G10,IF(E10="Partial",G10*0.5,0)) | I10: Security Reviewer
A11: IA-07 | B11: Mobile access path considered | C11: Phone browser to web UI, or a messaging app — not explicitly designed for yet. | D11: N/A (process/doc) | E11: Not Started | G11: 3 | H11: =IF(E11="Done",G11,IF(E11="Partial",G11*0.5,0)) | I11: Interface Engineer
A12: IA-08 | B12: Voice interface explicitly scoped or deferred | C12: Not a current goal — worth writing down as a deliberate non-goal rather than leaving it ambiguous. | D12: N/A (process/doc) | E12: Not Started | G12: 2 | H12: =IF(E12="Done",G12,IF(E12="Partial",G12*0.5,0)) | I12: Hermes Design Specialist | J12: DECIDED 2026-10-05: explicitly deferred, not part of this execution wave -- focus on core agent (memory/Telegram/local model/security) first.
A13: IA-09 | B13: Access logging per interface | C13: No record of who/when hit the web UI, Desktop, or future Telegram channel. | D13: Hermes-VPS | E13: Not Started | G13: 3 | H13: =IF(E13="Done",G13,IF(E13="Partial",G13*0.5,0)) | I13: Security Reviewer
A14: IA-10 | B14: TTS provider: Edge — locked in | C14: LOCKED 2026-10-04: Edge TTS, the Hermes default — free, no API key, 322 voices/74 languages. Low-stakes pick since voice is already a deferred non-goal elsewhere in this workbook; not worth more setup effort than the default. | D14: Hermes-VPS | E14: Partial | F14: hermes-five-provider-choices-locked-2026-10-04 | G14: 2 | H14: =IF(E14="Done",G14,IF(E14="Partial",G14*0.5,0)) | I14: Interface Engineer | J14: Decided, not yet confirmed configured (it may already be default-active with zero setup needed)
H15: =IF(E15="Done",G15,IF(E15="Partial",G15*0.5,0))
H16: =IF(E16="Done",G16,IF(E16="Partial",G16*0.5,0))
H17: =IF(E17="Done",G17,IF(E17="Partial",G17*0.5,0))
H18: =IF(E18="Done",G18,IF(E18="Partial",G18*0.5,0))
H19: =IF(E19="Done",G19,IF(E19="Partial",G19*0.5,0))
H20: =IF(E20="Done",G20,IF(E20="Partial",G20*0.5,0))
H21: =IF(E21="Done",G21,IF(E21="Partial",G21*0.5,0))
H22: =IF(E22="Done",G22,IF(E22="Partial",G22*0.5,0))
H23: =IF(E23="Done",G23,IF(E23="Partial",G23*0.5,0))
H24: =IF(E24="Done",G24,IF(E24="Partial",G24*0.5,0))
H25: =IF(E25="Done",G25,IF(E25="Partial",G25*0.5,0))
H26: =IF(E26="Done",G26,IF(E26="Partial",G26*0.5,0))
... H44: =IF(E44="Done",G44,IF(E44="Partial",G44*0.5,0))
B46: TAB TOTAL (includes blank headroom rows above for future additions) | G46: =SUM(G5:G44) | H46: =SUM(H5:H44) | I46: =IFERROR(TEXT(H46/G46,"0%")&" complete","0% complete")

Sheet 09_Observability
A1: Observability
A2: You should be able to tell Hermes is healthy without SSHing anywhere.
A4: ID | B4: Feature | C4: Description (execution level) | D4: Must Live On | E4: Status | F4: Evidence / Location | G4: Points | H4: Points Earned | I4: Owner Role | J4: Notes / Next Action
A5: OB-01 | B5: Routing-decision logging | C5: complexity_router.log captures every verdict + reason. | D5: Hermes-VPS | E5: Partial | F5: /home/hermes/.hermes/logs/complexity_router.log | G5: 3 | H5: =IF(E5="Done",G5,IF(E5="Partial",G5*0.5,0)) | I5: Observability | J5: Exists, nobody's watching it
A6: OB-02 | B6: Alerting: tunnel drop / local-model-down / minion-lost / Hermes crash | C6: No notification path to you exists for any of these today. | D6: Either / Bridge | E6: Not Started | G6: 10 | H6: =IF(E6="Done",G6,IF(E6="Partial",G6*0.5,0)) | I6: Observability
A7: OB-03 | B7: Unified health dashboard | C7: Local-vs-Codex indicator + tunnel status + VPS health, in one place. | D7: Hermes-VPS | E7: Not Started | G7: 8 | H7: =IF(E7="Done",G7,IF(E7="Partial",G7*0.5,0)) | I7: Observability
A8: OB-04 | B8: Beszel (or equivalent) coverage extended to hermes-vps | C8: Beszel watches home-lab boxes only; nothing watches the VPS from either side. | D8: Hermes-VPS | E8: Not Started | G8: 5 | H8: =IF(E8="Done",G8,IF(E8="Partial",G8*0.5,0)) | I8: Observability
A9: OB-05 | B9: Log retention/rotation policy | C9: No consistent policy across any Hermes-side log. | D9: Hermes-VPS | E9: Not Started | G9: 3 | H9: =IF(E9="Done",G9,IF(E9="Partial",G9*0.5,0)) | I9: Observability
A10: OB-06 | B10: Synthetic end-to-end health probe | C10: A scheduled test prompt that proves full aliveness, not just 'process is running.' | D10: Hermes-VPS | E10: Not Started | G10: 5 | H10: =IF(E10="Done",G10,IF(E10="Partial",G10*0.5,0)) | I10: Observability
H11: =IF(E11="Done",G11,IF(E11="Partial",G11*0.5,0))
H12: =IF(E12="Done",G12,IF(E12="Partial",G12*0.5,0))
H13: =IF(E13="Done",G13,IF(E13="Partial",G13*0.5,0))
H14: =IF(E14="Done",G14,IF(E14="Partial",G14*0.5,0))
H15: =IF(E15="Done",G15,IF(E15="Partial",G15*0.5,0))
H16: =IF(E16="Done",G16,IF(E16="Partial",G16*0.5,0))
H17: =IF(E17="Done",G17,IF(E17="Partial",G17*0.5,0))
H18: =IF(E18="Done",G18,IF(E18="Partial",G18*0.5,0))
H19: =IF(E19="Done",G19,IF(E19="Partial",G19*0.5,0))
H20: =IF(E20="Done",G20,IF(E20="Partial",G20*0.5,0))
H21: =IF(E21="Done",G21,IF(E21="Partial",G21*0.5,0))
H22: =IF(E22="Done",G22,IF(E22="Partial",G22*0.5,0))
... H40: =IF(E40="Done",G40,IF(E40="Partial",G40*0.5,0))
B42: TAB TOTAL (includes blank headroom rows above for future additions) | G42: =SUM(G5:G40) | H42: =SUM(H5:H40) | I42: =IFERROR(TEXT(H42/G42,"0%")&" complete","0% complete")

Sheet 10_Backup_DR
A1: Backup & Disaster Recovery
A2: If a box disappears tonight, what comes back, and how.
A4: ID | B4: Feature | C4: Description (execution level) | D4: Must Live On | E4: Status | F4: Evidence / Location | G4: Points | H4: Points Earned | I4: Owner Role | J4: Notes / Next Action
A5: BD-01 | B5: Catalog export + git backup | C5: export_catalog_memory.py dumps hermes-tagged entities/relations to memory/catalog-export.json, committed. | D5: N/A (process/doc) | E5: Done | F5: scripts/export_catalog_memory.py | G5: 5 | H5: =IF(E5="Done",G5,IF(E5="Partial",G5*0.5,0)) | I5: Platform/SRE
A6: BD-02 | B6: hermes-vps recurring backup | C6: Confirmed 2026-10-04 via the Vultr console: Auto Backups is Enabled on hermes-vps — a full-disk snapshot at the infrastructure level, broader than the earlier one-off app backup. Covers config.yaml/MEMORY.md/MCP venvs automatically. | D6: Hermes-VPS | E6: Done | F6: hermes-vps-vultr-auto-backups-enabled-2026-10-04 | G6: 10 | H6: =IF(E6="Done",G6,IF(E6="Partial",G6*0.5,0)) | I6: Platform/SRE | J6: Worth confirming restore has actually been tested (BD-05) despite backup existing
A7: BD-03 | B7: WordPress volume backup strategy | C7: Undefined since 2026-07-25, still true. | D7: Home-Network | E7: Not Started | F7: server wordpress_data/db_data | G7: 5 | H7: =IF(E7="Done",G7,IF(E7="Partial",G7*0.5,0)) | I7: Platform/SRE
A8: BD-04 | B8: Documented full-rebuild runbook | C8: Step-by-step recreate-from-nothing procedure for hermes-vps. | D8: N/A (process/doc) | E8: Not Started | G8: 8 | H8: =IF(E8="Done",G8,IF(E8="Partial",G8*0.5,0)) | I8: Hermes Design Specialist | J8: Found 2026-10-05: System dashboard page has built-in backup/restore and support-dump generation, plus hermes doctor -- candidates to use/document here instead of writing a runbook from scratch. See D6_Web_Dashboard.
A9: BD-05 | B9: Backup restore actually tested | C9: A backup that's never been restored is a hypothesis, not a backup. | D9: N/A (process/doc) | E9: Not Started | G9: 8 | H9: =IF(E9="Done",G9,IF(E9="Partial",G9*0.5,0)) | I9: Platform/SRE | J9: Found 2026-10-05: System dashboard page's built-in restore function is the natural thing to actually test for this row. See D6_Web_Dashboard.
A10: BD-06 | B10: Vault/secrets table backup | C10: Separate from the general catalog export — this is the crown jewel and deserves its own explicit backup story. | D10: Hermes-VPS | E10: Not Started | G10: 8 | H10: =IF(E10="Done",G10,IF(E10="Partial",G10*0.5,0)) | I10: Secrets Custodian
H11: =IF(E11="Done",G11,IF(E11="Partial",G11*0.5,0))
H12: =IF(E12="Done",G12,IF(E12="Partial",G12*0.5,0))
H13: =IF(E13="Done",G13,IF(E13="Partial",G13*0.5,0))
H14: =IF(E14="Done",G14,IF(E14="Partial",G14*0.5,0))
H15: =IF(E15="Done",G15,IF(E15="Partial",G15*0.5,0))
H16: =IF(E16="Done",G16,IF(E16="Partial",G16*0.5,0))
H17: =IF(E17="Done",G17,IF(E17="Partial",G17*0.5,0))
H18: =IF(E18="Done",G18,IF(E18="Partial",G18*0.5,0))
H19: =IF(E19="Done",G19,IF(E19="Partial",G19*0.5,0))
H20: =IF(E20="Done",G20,IF(E20="Partial",G20*0.5,0))
H21: =IF(E21="Done",G21,IF(E21="Partial",G21*0.5,0))
H22: =IF(E22="Done",G22,IF(E22="Partial",G22*0.5,0))
... H40: =IF(E40="Done",G40,IF(E40="Partial",G40*0.5,0))
B42: TAB TOTAL (includes blank headroom rows above for future additions) | G42: =SUM(G5:G40) | H42: =SUM(H5:H40) | I42: =IFERROR(TEXT(H42/G42,"0%")&" complete","0% complete")

Sheet 11_Cost_Subscriptions
A1: Cost & Subscriptions
A2: The whole point: one paid tier instead of two.
A4: ID | B4: Feature | C4: Description (execution level) | D4: Must Live On | E4: Status | F4: Evidence / Location | G4: Points | H4: Points Earned | I4: Owner Role | J4: Notes / Next Action
A5: CS-01 | B5: ChatGPT Plus linked, Codex working | C5: $20/mo, already doing real work. | D5: Hermes-VPS | E5: Done | G5: 3 | H5: =IF(E5="Done",G5,IF(E5="Partial",G5*0.5,0)) | I5: Product Owner (Mark)
A6: CS-02 | B6: Vultr VPS + backups cost tracked | C6: vhp-2c-4gb-amd @ $24/mo + daily-snapshot backups at $4.80/mo (Vultr's standard 20%-of-instance add-on, not $4.80/day) = $28.80/mo total. | D6: Hermes-VPS | E6: Done | F6: hermes-vps-provider-selected-vultr-2026-09-24 | G6: 2 | H6: =IF(E6="Done",G6,IF(E6="Partial",G6*0.5,0)) | I6: Product Owner (Mark)
A7: CS-03 | B7: Claude Pro canceled | C7: Intentionally last — this is the actual finish line of the whole project (G9). | D7: N/A (process/doc) | E7: Not Started | G7: 10 | H7: =IF(E7="Done",G7,IF(E7="Partial",G7*0.5,0)) | I7: Product Owner (Mark) | J7: Only cancel once the rest of this workbook is actually green
A8: CS-04 | B8: Modal cost visibility | C8: Pay-per-second, $0 idle — confirm no surprise charges are actually possible, not just assumed. | D8: Hermes-VPS | E8: Not Started | G8: 3 | H8: =IF(E8="Done",G8,IF(E8="Partial",G8*0.5,0)) | I8: Product Owner (Mark)
A9: CS-05 | B9: Total monthly Hermes cost rollup | C9: One number to compare against the 'two subscriptions' baseline being replaced. | D9: N/A (process/doc) | E9: Not Started | G9: 3 | H9: =IF(E9="Done",G9,IF(E9="Partial",G9*0.5,0)) | I9: Product Owner (Mark) | J9: Found 2026-10-05: dashboard has a built-in Analytics page (token counts, cache hit rates, estimated costs, per-model breakdown, 7/30/90-day windows) -- check this before building any custom cost rollup. See D6_Web_Dashboard.
A10: CS-06 | B10: Brave Search free-tier usage monitored | C10: 2,000 queries/mo free tier — nothing watches for approaching that ceiling. | D10: Hermes-VPS | E10: Not Started | G10: 2 | H10: =IF(E10="Done",G10,IF(E10="Partial",G10*0.5,0)) | I10: Observability
H11: =IF(E11="Done",G11,IF(E11="Partial",G11*0.5,0))
H12: =IF(E12="Done",G12,IF(E12="Partial",G12*0.5,0))
H13: =IF(E13="Done",G13,IF(E13="Partial",G13*0.5,0))
H14: =IF(E14="Done",G14,IF(E14="Partial",G14*0.5,0))
H15: =IF(E15="Done",G15,IF(E15="Partial",G15*0.5,0))
H16: =IF(E16="Done",G16,IF(E16="Partial",G16*0.5,0))
H17: =IF(E17="Done",G17,IF(E17="Partial",G17*0.5,0))
H18: =IF(E18="Done",G18,IF(E18="Partial",G18*0.5,0))
H19: =IF(E19="Done",G19,IF(E19="Partial",G19*0.5,0))
H20: =IF(E20="Done",G20,IF(E20="Partial",G20*0.5,0))
H21: =IF(E21="Done",G21,IF(E21="Partial",G21*0.5,0))
H22: =IF(E22="Done",G22,IF(E22="Partial",G22*0.5,0))
... H40: =IF(E40="Done",G40,IF(E40="Partial",G40*0.5,0))
B42: TAB TOTAL (includes blank headroom rows above for future additions) | G42: =SUM(G5:G40) | H42: =SUM(H5:H40) | I42: =IFERROR(TEXT(H42/G42,"0%")&" complete","0% complete")

Sheet 12_Security_Hardening
A1: Security & Hardening
A2: Everything here is a closeable gap, not a design debate.
A4: ID | B4: Feature | C4: Description (execution level) | D4: Must Live On | E4: Status | F4: Evidence / Location | G4: Points | H4: Points Earned | I4: Owner Role | J4: Notes / Next Action
A5: SH-01 | B5: VPS firewall active | C5: Duplicate reference to CR-04 — owned here for remediation tracking. | D5: Hermes-VPS | E5: Done | G5: 3 | H5: =IF(E5="Done",G5,IF(E5="Partial",G5*0.5,0)) | I5: Security Reviewer
A6: SH-02 | B6: Gateway arbitrary-shell exposure closed | C6: Same underlying item as 06_Home_Network_Boundary HN-05 — cross-referenced here as Security's responsibility to actually close; scored at HN-05, not twice. | D6: Hermes-VPS | E6: Not Started | G6: 0 | H6: =IF(E6="Done",G6,IF(E6="Partial",G6*0.5,0)) | I6: Security Reviewer | J6: Cross-reference of HN-05, not separately weighted
A7: SH-03 | B7: /Dockers plaintext secrets exposure remediated | C7: Same underlying item as 05_Secrets_Vault SV-08; cross-referenced here, scored there. | D7: Home-Network | E7: Not Started | G7: 0 | H7: =IF(E7="Done",G7,IF(E7="Partial",G7*0.5,0)) | I7: Security Reviewer | J7: Cross-reference of SV-08, not separately weighted
A8: SH-04 | B8: Least-privilege review, all MCP credentials | C8: Same item as TM-11. | D8: Either / Bridge | E8: Done | F8: hermes-vps config.yaml mcp_servers.infra.env (SALT_USER/SALT_PASS now ${VAR} interpolated from .env, verified real values land in the MCP subprocess env, not plaintext in config.yaml) | G8: 5 | H8: =IF(E8="Done",G8,IF(E8="Partial",G8*0.5,0)) | I8: Security Reviewer | J8: FIXED 2026-10-05: found SALT_PASS/SALT_USER hardcoded in plaintext in config.yaml for the infra MCP server (Salt eauth creds). Confirmed hermes-agent supports ${VAR} interpolation for mcp_servers.*.env (per mcp_startup.py). Moved both to .env (chmod 600), switched config.yaml to ${SALT_USER}/${SALT_PASS}, restarted gateway, verified via /proc/<pid>/environ that the real values still reach the subprocess. Other MCP servers (catalog, search, vault) already used this pattern or had no inline secret.
A9: SH-05 | B9: Tunnel ACL minimum-exposure audit | C9: Same item as HN-07. | D9: Home-Network | E9: Not Started | G9: 5 | H9: =IF(E9="Done",G9,IF(E9="Partial",G9*0.5,0)) | I9: Security Reviewer
A10: SH-06 | B10: Web UI auth mechanism security review | C10: Basic Auth vs. app-login — security implications of each never compared. | D10: Hermes-VPS | E10: Done | F10: config.yaml dashboard.basic_auth: scrypt password_hash set, username=hermes; fronted by Caddy Basic Auth; live 401 check 2026-10-05 | G10: 5 | H10: =IF(E10="Done",G10,IF(E10="Partial",G10*0.5,0)) | I10: Security Reviewer | J10: RESOLVED 2026-10-05: confirmed the dashboard auth provider is app-level password/basic_auth (scrypt-hashed, not plaintext, not OAuth/OIDC), double-gated behind Caddy's own Basic Auth. Matches the catalog's hermes-vps-dashboard-basic-auth / hermes-vps-caddy-basic-auth secret entries. No weaker-than-expected auth found.
A11: SH-07 | B11: Dependency/CVE awareness process | C11: hermes-agent, FastMCP, and MCP server deps have no update-for-CVE process. | D11: Either / Bridge | E11: Partial | F11: hermes security audit run 2026-10-05: 68 findings across 106 components (venv deps: PyJWT, httpx2, urllib3, oauthlib, plus hermes-agent itself showing as 0.0.0 to the OSV scanner - likely a git-install version-metadata quirk given the real running version is v0.21.5+4477, not an untouched ancient install) | G11: 5 | H11: =IF(E11="Done",G11,IF(E11="Partial",G11*0.5,0)) | I11: Security Reviewer | J11: PROCESS now exists and was run (closes the 'no process' gap) but real findings surfaced, not yet remediated: PyJWT 2.13.0 has several HIGH/CRITICAL CVEs fixed in 2.14.0; httpx2/urllib3/oauthlib also behind. Separately, dashboard already flags hermes-agent itself as 2547 commits behind (CR-11, Not Started, owns the 'when to hermes update' decision) - that update would likely also resolve the hermes-agent==0.0.0 scanner artifact. Recommend: bump the 4 flagged deps in the venv directly as a quick win, treat the full hermes update as CR-11's call, not bundled in here.
A12: SH-08 | B12: Credential-leak incident response notes | C12: Given the /Dockers exposure already exists, what's the actual response if one of those leaks gets used? | D12: N/A (process/doc) | E12: Not Started | G12: 5 | H12: =IF(E12="Done",G12,IF(E12="Partial",G12*0.5,0)) | I12: Security Reviewer
H13: =IF(E13="Done",G13,IF(E13="Partial",G13*0.5,0))
H14: =IF(E14="Done",G14,IF(E14="Partial",G14*0.5,0))
H15: =IF(E15="Done",G15,IF(E15="Partial",G15*0.5,0))
H16: =IF(E16="Done",G16,IF(E16="Partial",G16*0.5,0))
H17: =IF(E17="Done",G17,IF(E17="Partial",G17*0.5,0))
H18: =IF(E18="Done",G18,IF(E18="Partial",G18*0.5,0))
H19: =IF(E19="Done",G19,IF(E19="Partial",G19*0.5,0))
H20: =IF(E20="Done",G20,IF(E20="Partial",G20*0.5,0))
H21: =IF(E21="Done",G21,IF(E21="Partial",G21*0.5,0))
H22: =IF(E22="Done",G22,IF(E22="Partial",G22*0.5,0))
H23: =IF(E23="Done",G23,IF(E23="Partial",G23*0.5,0))
H24: =IF(E24="Done",G24,IF(E24="Partial",G24*0.5,0))
... H42: =IF(E42="Done",G42,IF(E42="Partial",G42*0.5,0))
B44: TAB TOTAL (includes blank headroom rows above for future additions) | G44: =SUM(G5:G42) | H44: =SUM(H5:H42) | I44: =IFERROR(TEXT(H44/G44,"0%")&" complete","0% complete")

Sheet 13_Governance_Change_Mgmt
A1: Governance & Change Management
A2: How this whole system stays coherent as it grows, instead of drifting back into a mixed environment.
A4: ID | B4: Feature | C4: Description (execution level) | D4: Must Live On | E4: Status | F4: Evidence / Location | G4: Points | H4: Points Earned | I4: Owner Role | J4: Notes / Next Action
A5: GV-01 | B5: Playbook: promote a home capability to a Hermes tool | C5: Same item as TM-10 — owned here as the actual governance process, not just a tooling note. | D5: N/A (process/doc) | E5: Not Started | G5: 5 | H5: =IF(E5="Done",G5,IF(E5="Partial",G5*0.5,0)) | I5: Hermes Design Specialist
A6: GV-02 | B6: Claude-Code-as-bootstrap sunset plan | C6: CLAUDE.md already states the setup role should eventually move into Hermes itself — no plan yet for when/how that actually happens. | D6: N/A (process/doc) | E6: Not Started | G6: 8 | H6: =IF(E6="Done",G6,IF(E6="Partial",G6*0.5,0)) | I6: Hermes Design Specialist | J6: See 14_Claude_Code_Parity for the concrete per-capability breakdown of what this actually requires Found 2026-10-05: hermes import-agent (imports an existing ~/.claude or ~/.codex setup directly into a Hermes profile) may literally BE this sunset mechanism, not something to design from scratch. See D8_Advanced_Reference.
A7: GV-03 | B7: Change log for hermes-vps config.yaml edits | C7: No approval/record process for who changed what on the live config. | D7: Hermes-VPS | E7: Not Started | G7: 5 | H7: =IF(E7="Done",G7,IF(E7="Partial",G7*0.5,0)) | I7: Hermes Design Specialist | J7: Found 2026-10-05: Checkpoints & Rollback feature auto-snapshots before every file write/destructive command into a shadow git repo (~/.hermes/checkpoints/store/), with /rollback <N> undo -- an implicit, automatic change history for config.yaml and everything else Hermes touches. Check before building a separate changelog. See D6_Web_Dashboard.
A8: GV-04 | B8: Role definitions actively assigned per feature | C8: This workbook's own Roles tab needs to actually get used, not just exist. | D8: N/A (process/doc) | E8: Not Started | G8: 3 | H8: =IF(E8="Done",G8,IF(E8="Partial",G8*0.5,0)) | I8: Hermes Design Specialist
A9: GV-05 | B9: Hermes Way standards re-checked on every new capability | C9: The recursive-completeness habit that built this workbook needs to repeat each time something new is added, not happen once. | D9: N/A (process/doc) | E9: Not Started | G9: 5 | H9: =IF(E9="Done",G9,IF(E9="Partial",G9*0.5,0)) | I9: Hermes Design Specialist
A10: GV-06 | B10: Catalog <-> workbook cross-linked | C10: Avoid this spreadsheet and the catalog silently becoming two different sources of truth. | D10: N/A (process/doc) | E10: Not Started | G10: 5 | H10: =IF(E10="Done",G10,IF(E10="Partial",G10*0.5,0)) | I10: Hermes Design Specialist
H11: =IF(E11="Done",G11,IF(E11="Partial",G11*0.5,0))
H12: =IF(E12="Done",G12,IF(E12="Partial",G12*0.5,0))
H13: =IF(E13="Done",G13,IF(E13="Partial",G13*0.5,0))
H14: =IF(E14="Done",G14,IF(E14="Partial",G14*0.5,0))
H15: =IF(E15="Done",G15,IF(E15="Partial",G15*0.5,0))
H16: =IF(E16="Done",G16,IF(E16="Partial",G16*0.5,0))
H17: =IF(E17="Done",G17,IF(E17="Partial",G17*0.5,0))
H18: =IF(E18="Done",G18,IF(E18="Partial",G18*0.5,0))
H19: =IF(E19="Done",G19,IF(E19="Partial",G19*0.5,0))
H20: =IF(E20="Done",G20,IF(E20="Partial",G20*0.5,0))
H21: =IF(E21="Done",G21,IF(E21="Partial",G21*0.5,0))
H22: =IF(E22="Done",G22,IF(E22="Partial",G22*0.5,0))
... H40: =IF(E40="Done",G40,IF(E40="Partial",G40*0.5,0))
B42: TAB TOTAL (includes blank headroom rows above for future additions) | G42: =SUM(G5:G40) | H42: =SUM(H5:H40) | I42: =IFERROR(TEXT(H42/G42,"0%")&" complete","0% complete")

Sheet 14_Claude_Code_Parity
A1: Claude Code → Hermes Parity
A2: The replacement lens: for everything Claude Code does on this project today, what Hermes-native capability would need to do it instead — so Claude Code can actually be retired, not just described as temporary.
A4: ID | B4: Feature | C4: Description (execution level) | D4: Must Live On | E4: Status | F4: Evidence / Location | G4: Points | H4: Points Earned | I4: Owner Role | J4: Notes / Next Action
A5: CCP-01 | B5: Catalog read/write parity | C5: Claude Code drives catalog_mcp.py by hand each session. The tool itself already runs on hermes-vps (TM-01) — the gap is usage, not capability: Hermes isn't the one calling it as part of its own memory loop yet. | D5: Hermes-VPS | E5: Partial | F5: TM-01 | G5: 5 | H5: =IF(E5="Done",G5,IF(E5="Partial",G5*0.5,0)) | I5: Hermes Design Specialist | J5: Tool parity exists; usage parity doesn't
A6: CCP-02 | B6: Vault secret access parity | C6: Same gap as CCP-01, blocked further by the 4x vault_mcp.py duplication. | D6: Hermes-VPS | E6: Not Started | F6: TM-06 / SV-12 | G6: 5 | H6: =IF(E6="Done",G6,IF(E6="Partial",G6*0.5,0)) | I6: Secrets Custodian | J6: Consolidate first, then shift usage to Hermes
A7: CCP-03 | B7: Salt/infra command parity | C7: infra_mcp.py already registered on hermes-vps (TM-04) — same usage-parity gap as CCP-01. | D7: Hermes-VPS | E7: Partial | F7: TM-04 | G7: 5 | H7: =IF(E7="Done",G7,IF(E7="Partial",G7*0.5,0)) | I7: Home-Network Liaison
A8: CCP-04 | B8: Git repository upkeep (commit/push) | C8: Claude Code commits/pushes to this repo via direct shell git commands on this laptop. No Hermes-native equivalent exists at all — Hermes would need a git/GitHub-aware tool (wrapping gh/git with its own deploy key) reachable from hermes-vps. | D8: Either / Bridge | E8: Not Started | G8: 8 | H8: =IF(E8="Done",G8,IF(E8="Partial",G8*0.5,0)) | I8: Hermes Design Specialist | J8: Real gap, not just a usage shift — nothing lets Hermes itself touch this repo today
A9: CCP-05 | B9: Repo file editing / code changes | C9: Claude Code edits this project's files directly via local tools. Hermes-native equivalent would be one of its sandboxed execution backends (local/Docker/SSH/Modal) pointed at the repo. | D9: Either / Bridge | E9: Not Started | G9: 8 | H9: =IF(E9="Done",G9,IF(E9="Partial",G9*0.5,0)) | I9: Hermes Design Specialist
A10: CCP-06 | B10: Document / spreadsheet generation | C10: This very workbook was built with openpyxl in a local venv. No Hermes-native equivalent — would need a scripting execution backend (Modal job or Dokploy-hosted script) capable of the same generation step. | D10: Hermes-VPS | E10: Not Started | G10: 5 | H10: =IF(E10="Done",G10,IF(E10="Partial",G10*0.5,0)) | I10: Platform/SRE
A11: CCP-07 | B11: Shareable web output | C11: Claude Code used Claude.ai's own Artifact tool for the earlier status page. The direct Hermes-native analogue is already tracked as CR-08 (Hermes-hosted web presence) — this row just names the Claude-Code-specific trigger for closing it. | D11: Hermes-VPS | E11: Not Started | F11: CR-08 | G11: 3 | H11: =IF(E11="Done",G11,IF(E11="Partial",G11*0.5,0)) | I11: Hermes Design Specialist
A12: CCP-08 | B12: Web search / page fetch | C12: Claude Code has its own WebSearch/WebFetch tools; Hermes's search_mcp.py (TM-02) is the preferred native path and already works. | D12: Hermes-VPS | E12: Done | F12: TM-02 | G12: 3 | H12: =IF(E12="Done",G12,IF(E12="Partial",G12*0.5,0)) | I12: Platform/SRE | J12: Tool parity already achieved here
A13: CCP-09 | B13: Browser automation | C13: Claude Code has dedicated browser tools; Nous's native Tool Gateway advertises browser automation too, but it's unconfirmed/uncredentialed (same item as TM-07). | D13: Hermes-VPS | E13: Not Started | F13: TM-07 | G13: 3 | H13: =IF(E13="Done",G13,IF(E13="Partial",G13*0.5,0)) | I13: Platform/SRE
A14: CCP-10 | B14: Scheduled / recurring tasks | C14: Claude Code's environment can schedule wakeups/cron jobs for this kind of work; whether hermes-agent exposes an equivalent internal scheduler is unconfirmed. | D14: Hermes-VPS | E14: Not Started | G14: 5 | H14: =IF(E14="Done",G14,IF(E14="Partial",G14*0.5,0)) | I14: Hermes Design Specialist | J14: Needed for things like secret-rotation reminders or nightly backup checks once those exist
A15: CCP-11 | B15: Session / multi-step task tracking | C15: Claude Code tracks its own task lists mid-session; unconfirmed whether hermes-agent has anything similar for tracking its own multi-step work. | D15: Hermes-VPS | E15: Not Started | G15: 2 | H15: =IF(E15="Done",G15,IF(E15="Partial",G15*0.5,0)) | I15: Hermes Design Specialist
A16: CCP-12 | B16: Full bootstrap retirement criterion | C16: The actual 'replace Claude Code with Hermes' finish line: every row above at parity, AND Hermes can perform this project's real maintenance (memory, git, infra) without Claude Code ever being opened. | D16: N/A (process/doc) | E16: Not Started | G16: 10 | H16: =IF(E16="Done",G16,IF(E16="Partial",G16*0.5,0)) | I16: Hermes Design Specialist | J16: This is GV-02's concrete success criterion
H17: =IF(E17="Done",G17,IF(E17="Partial",G17*0.5,0))
H18: =IF(E18="Done",G18,IF(E18="Partial",G18*0.5,0))
H19: =IF(E19="Done",G19,IF(E19="Partial",G19*0.5,0))
H20: =IF(E20="Done",G20,IF(E20="Partial",G20*0.5,0))
H21: =IF(E21="Done",G21,IF(E21="Partial",G21*0.5,0))
H22: =IF(E22="Done",G22,IF(E22="Partial",G22*0.5,0))
H23: =IF(E23="Done",G23,IF(E23="Partial",G23*0.5,0))
H24: =IF(E24="Done",G24,IF(E24="Partial",G24*0.5,0))
H25: =IF(E25="Done",G25,IF(E25="Partial",G25*0.5,0))
H26: =IF(E26="Done",G26,IF(E26="Partial",G26*0.5,0))
H27: =IF(E27="Done",G27,IF(E27="Partial",G27*0.5,0))
H28: =IF(E28="Done",G28,IF(E28="Partial",G28*0.5,0))
... H46: =IF(E46="Done",G46,IF(E46="Partial",G46*0.5,0))
B48: TAB TOTAL (includes blank headroom rows above for future additions) | G48: =SUM(G5:G46) | H48: =SUM(H5:H46) | I48: =IFERROR(TEXT(H48/G48,"0%")&" complete","0% complete")

Sheet 15_Productivity_And_Acceptance
A1: Productivity & Acceptance Testing
A2: What you actually get done through Hermes, and how to prove it works end-to-end — not just 'the service is running.' Flagged as a real coverage gap: the first 14 tabs are almost entirely infrastructure.
A4: ID | B4: Feature | C4: Description (execution level) | D4: Must Live On | E4: Status | F4: Evidence / Location | G4: Points | H4: Points Earned | I4: Owner Role | J4: Notes / Next Action
A5: PA-01 | B5: Google Drive file find/open/edit | C5: Locate and edit an existing file in Drive by name/content, not just by exact path. | D5: Hermes-VPS | E5: Not Started | F5: hermes-google-office-preference-2026-10-04 | G5: 5 | H5: =IF(E5="Done",G5,IF(E5="Partial",G5*0.5,0)) | I5: Interface Engineer | J5: User prefers Google's office ecosystem for agentic work — no integration exists yet
A6: PA-02 | B6: Create/edit Docs, Sheets, Slides | C6: Produce a real Doc/Sheet/Slide deck from a request, not just a local file Hermes can't put anywhere the user already works. | D6: Hermes-VPS | E6: Not Started | G6: 8 | H6: =IF(E6="Done",G6,IF(E6="Partial",G6*0.5,0)) | I6: Interface Engineer
A7: PA-03 | B7: Gmail workflow (read/draft/send) | C7: At minimum: search mail, draft a reply, send with confirmation for anything irreversible. | D7: Hermes-VPS | E7: Not Started | G7: 5 | H7: =IF(E7="Done",G7,IF(E7="Partial",G7*0.5,0)) | I7: Interface Engineer
A8: PA-04 | B8: Calendar workflow (read/create/respond) | C8: Check availability, create an event, respond to an invite. | D8: Hermes-VPS | E8: Not Started | G8: 5 | H8: =IF(E8="Done",G8,IF(E8="Partial",G8*0.5,0)) | I8: Interface Engineer
A9: PA-05 | B9: Finished-deliverable acceptance test | C9: Produce an artifact (doc, sheet, code, report), inspect its own layout/calculations for correctness, revise it, and deliver it somewhere the user can actually use it — not just 'file was created.' | D9: N/A (process/doc) | E9: Not Started | G9: 8 | H9: =IF(E9="Done",G9,IF(E9="Partial",G9*0.5,0)) | I9: Hermes Design Specialist | J9: This is the actual test this workbook itself should pass once Hermes builds things like it
A10: PA-06 | B10: Persistent project continuity | C10: Resume work on a named project across sessions, retain its decisions, distinguish it from other concurrent projects, and correct an outdated memory when told it's wrong. | D10: Hermes-VPS | E10: Not Started | G10: 10 | H10: =IF(E10="Done",G10,IF(E10="Partial",G10*0.5,0)) | I10: Hermes Design Specialist | J10: Overlaps 02_Identity_Memory but from the angle of multiple concurrent projects, not just single-identity continuity
A11: PA-07 | B11: Long-running work: schedule/monitor/notify | C11: Schedule a task, monitor it to completion, notify the user without repeating actions already done. | D11: Hermes-VPS | E11: Not Started | G11: 8 | H11: =IF(E11="Done",G11,IF(E11="Partial",G11*0.5,0)) | I11: Hermes Design Specialist
A12: PA-08 | B12: Long-running work: pause/cancel/resume-after-failure | C12: The harder half of PA-07 — recovering a long task after a crash or interruption without starting over or duplicating completed steps. | D12: Hermes-VPS | E12: Not Started | G12: 8 | H12: =IF(E12="Done",G12,IF(E12="Partial",G12*0.5,0)) | I12: Hermes Design Specialist
A13: PA-09 | B13: Agent behavior: permitted-actions policy | C13: A written definition of what Hermes may do autonomously vs. needs confirmation for — the Hermes equivalent of this session's own instruction-source-boundary rules. | D13: N/A (process/doc) | E13: Not Started | G13: 8 | H13: =IF(E13="Done",G13,IF(E13="Partial",G13*0.5,0)) | I13: Hermes Design Specialist
A14: PA-10 | B14: Agent behavior: untrusted-content handling | C14: How Hermes treats instructions it finds inside documents/emails/web pages it's asked to process — should never treat embedded text as commands from the user. | D14: N/A (process/doc) | E14: Not Started | G14: 8 | H14: =IF(E14="Done",G14,IF(E14="Partial",G14*0.5,0)) | I14: Security Reviewer
A15: PA-11 | B15: Agent behavior: tool-failure recovery | C15: What Hermes does when a tool call fails mid-task — retry, degrade, or stop and ask — needs to be a defined behavior, not whatever happens by accident. | D15: Hermes-VPS | E15: Not Started | G15: 5 | H15: =IF(E15="Done",G15,IF(E15="Partial",G15*0.5,0)) | I15: Hermes Design Specialist
A16: PA-12 | B16: Acceptance testing as a standing practice | C16: Prove complete user workflows with observable results (a sent email, a usable spreadsheet, a working deploy) as the actual definition of 'done' — not 'tool installed' or 'service running,' which the rest of this workbook leans on heavily. | D16: N/A (process/doc) | E16: Not Started | G16: 8 | H16: =IF(E16="Done",G16,IF(E16="Partial",G16*0.5,0)) | I16: Hermes Design Specialist | J16: Direct response to this tab's own review feedback — apply this standard to every other tab's Done rows too, retroactively, as time allows
H17: =IF(E17="Done",G17,IF(E17="Partial",G17*0.5,0))
H18: =IF(E18="Done",G18,IF(E18="Partial",G18*0.5,0))
H19: =IF(E19="Done",G19,IF(E19="Partial",G19*0.5,0))
H20: =IF(E20="Done",G20,IF(E20="Partial",G20*0.5,0))
H21: =IF(E21="Done",G21,IF(E21="Partial",G21*0.5,0))
H22: =IF(E22="Done",G22,IF(E22="Partial",G22*0.5,0))
H23: =IF(E23="Done",G23,IF(E23="Partial",G23*0.5,0))
H24: =IF(E24="Done",G24,IF(E24="Partial",G24*0.5,0))
H25: =IF(E25="Done",G25,IF(E25="Partial",G25*0.5,0))
H26: =IF(E26="Done",G26,IF(E26="Partial",G26*0.5,0))
H27: =IF(E27="Done",G27,IF(E27="Partial",G27*0.5,0))
H28: =IF(E28="Done",G28,IF(E28="Partial",G28*0.5,0))
... H46: =IF(E46="Done",G46,IF(E46="Partial",G46*0.5,0))
B48: TAB TOTAL (includes blank headroom rows above for future additions) | G48: =SUM(G5:G46) | H48: =SUM(H5:H46) | I48: =IFERROR(TEXT(H48/G48,"0%")&" complete","0% complete")

Sheet D1_Vultr_Services_Audit
A1: Discovery — Vultr Services Audit
A2: What Vultr actually offers, researched 2026-10-04, mapped against whether Hermes should use it. Reference material, not a tracked backlog — the resulting action items live in the 01-15 tabs, not here.
A4: Service | B4: What it does | C4: Relevant to Hermes? | D4: Why | E4: Priority
A5: Cloud Compute (High Performance AMD) | B5: VPS tiers — the box Hermes itself runs on. | C5: Already using | D5: hermes-vps is this; sister's agent (CR-15) will be a second one. | E5: N/A — in use
A6: Managed Database (Postgres, MySQL, Valkey, Kafka) | B6: Fully-managed DB, $3.50/mo+, pgvector support free. | C6: Yes — high priority | D6: Direct fix for SV-15 (catalog/vault migration off fileserver) and a possible shared store for Hindsight (IM-05). | E6: High — tracked as SV-15
A7: Serverless Inference | B7: Pay-per-token hosted LLMs, pre-configured on hermes-vps already. | C7: Already using (idle) | D7: Real fallback tier between free-local and paid-Codex — priced out this session. | E7: Medium — reactivate as a fallback
A8: Object Storage (S3-compatible) | B8: Cheap unstructured storage, multiple tiers. | C8: Yes | D8: Natural backup destination for BD-02/BD-06. | E8: Medium
A9: Cloud Firewall | B9: Managed network-level firewall, separate from the VPS's own ufw. | C9: Yes | D9: Could close HN-05/SH-02 (gateway shell exposure) at the network layer, not just the app config layer — a second line of defense. | E9: High — security-relevant
A10: VPC (private networking) | B10: Private network between your Vultr instances, no public IP needed between them. | C10: Yes, once there's >1 instance | D10: Once sister's VPS (CR-15) and/or a Managed Database (SV-15) exist, VPC lets them talk to hermes-vps privately instead of over the public internet. | E10: Medium — do alongside SV-15/CR-15
A11: Block Storage | B11: Expandable disk volumes you attach to a VPS. | C11: Maybe | D11: hermes-vps's 100GB NVMe could get tight once memory providers/skills accumulate data; not urgent yet. | E11: Low — watch CR-12 (resource headroom)
A12: Cloud GPU / Bare Metal (GPU options) | B12: On-demand or dedicated GPU instances. | C12: Worth knowing, not recommended now | D12: Could theoretically host the local model on Vultr instead of w_workstation, which would fully remove the WireGuard-down dependency (MR-05) — but at real GPU-instance cost, undercutting the whole 'free local inference' point of using owned hardware. | E12: Low — only if the home-GPU approach is abandoned later
A13: Kubernetes (VKE) | B13: Managed container orchestration, free control plane. | C13: No | D13: Overkill for one VPS running one agent; relevant only if Hermes sprawls into many containerized services. | E13: Not now
A14: Container Registry | B14: Stores container images Hermes/Dokploy might build. | C14: Already tracked (TM-07 area) | D14: Free tier (10GB) covers this until custom images become a real need. | E14: Low
A15: CDN | B15: Edge caching for static assets. | C15: Minor | D15: Only relevant once CR-08 (Hermes-hosted web presence) exists and has real traffic. | E15: Low — revisit after CR-08
... A18: Load Balancers / NAT Gateway / Direct Connect | B18: HA traffic distribution, private hybrid-cloud links. | C18: No | D18: Enterprise/multi-instance-at-scale features; nothing here operates at that scale. | E18: Not applicable

Sheet D2_Providers_And_Deps
A1: Discovery — Providers Still Unchosen, and Dependencies of What's Locked
A2: Researched 2026-10-04. Two things in one tab: (1) provider categories found that have zero decision yet, (2) the real install/setup dependencies behind the five providers already locked in. Reference material — not a tracked backlog.
A4: Topic | B4: What it is | C4: Options found | D4: Recommendation / dependency detail | E4: Status
A5: STT (speech-to-text) | B5: Separate from TTS — converts your voice input to text. Not yet chosen. | C5: local/faster-whisper (free, on-box), groq (fast cloud), openai, mistral, xai, elevenlabs, telnyx, deepinfra | D5: Recommend local/faster-whisper — free, matches every other 'self-hosted preferred' choice made this session, no new credential needed. | E5: Not chosen — not yet asked about
A6: Image generation | B6: Routed through FAL.ai regardless of which model — not self-hostable. | C6: FLUX 2 Klein/Pro, GPT-Image 1.5/2, Nano Banana Pro, Ideogram V3, Recraft V4 Pro, Qwen, Z-Image Turbo, Krea V2 | D6: No free/local option exists for this one, unlike everything else — only relevant if image generation is actually wanted. Needs its own cost conversation if so. | E6: Not chosen — not yet asked about
A7: Browser automation backend | B7: What drives Hermes's browser-use tool capability (TM-07). | C7: Browserbase (cloud), Browser Use (cloud), local Chrome/Brave/Chromium/Edge via CDP, Camofox (local, anti-detection) | D7: Local CDP (e.g. local Chrome) is the free/self-hosted-matching option. Cloud options exist if local browsing proves unreliable. | E7: Not chosen — not yet asked about
A8: Embedding provider | B8: Powers RAG/semantic search — resolves the catalog's long-idle search_similar RPC (mentioned since the original 2026-09-25 local-model plan, nomic-embed-text). | C8: local/fastembed (e.g. all-MiniLM-L6-v2, free), openai, ollama | D8: Recommend local/fastembed — same reasoning as STT. This is also what would let Hindsight (IM-05) or the catalog do real semantic recall instead of exact-match search. | E8: Not chosen — not yet asked about
A9: DEPENDENCY: ik_llama.cpp (LI-03) on Windows | B9: Build requirements for the locked-in runtime. | C9: cmake, C++17 compiler, CUDA 12.6 Toolkit, Visual Studio Build Tools 2022 | D9: Env vars needed: VS_DIR, LLVM_DIR, CUDA_DIR (pointing at the CUDA 12.6 install path). Official build docs: github.com/ikawrakow/ik_llama.cpp/blob/main/docs/build.md | E9: Known, not yet done
A10: DEPENDENCY: Docker terminal backend (CR-17) | B10: What the locked-in terminal backend needs. | C10: Docker — already installed on hermes-vps for Dokploy | D10: Likely just a config.yaml change (terminal.backend: docker) plus picking a base image; no new install expected. | E10: Likely low-effort, unconfirmed
A11: DEPENDENCY: Telegram gateway (IA-05) | B11: What the locked-in messaging channel needs. | C11: A BotFather-issued bot token; your own numeric Telegram user ID | D11: 5 steps: message @BotFather, /newbot, name it, copy the token (format 123456789:ABC...), get your user ID from @userinfobot, run hermes gateway setup, paste both, start the gateway. Token is a real credential — vault it, don't leave it in config.yaml plaintext. | E11: Known, not yet done — new vault-worthy secret
A12: DEPENDENCY: Vultr fallback model (MR-13) | B12: What DeepSeek-V4-Flash needs beyond what exists. | C12: Already pre-configured/credentialed on hermes-vps | D12: Just needs an explicit fallback_providers entry in config.yaml — no new install or credential. | E12: Trivial, not yet done
A13: DEPENDENCY: Edge TTS (IA-10) | B13: What the locked-in TTS default needs. | C13: None — it's the Hermes default | D13: May already be active with zero configuration. Worth a quick hermes config show to confirm rather than assuming. | E13: Likely already satisfied, unconfirmed

Sheet D3_Skills_System
A1: Discovery — Skills System (Five Pillars: Skills)
A2: Researched 2026-10-04. How hermes-agent's Skills pillar actually works: what a skill is, how it's stored/loaded, bundled vs optional, self-authored creation, security scanning. Reference material — not a tracked backlog. Sources: hermes-agent.nousresearch.com/docs (user-guide/features/skills, guides/work-with-skills, reference/skills-catalog, reference/optional-skills-catalog).
A4: Topic | B4: What it is | C4: Options found | D4: Recommendation / dependency detail | E4: Status
A5: What a skill is | B5: An on-demand knowledge document the agent loads when needed — procedural memory for recurring tasks, not a one-off prompt. | C5: SKILL.md with YAML frontmatter (name, description, version, metadata.hermes: tags/category/platforms/requires_toolsets/config) + body sections (When to Use, Procedure, Pitfalls, Verification). Compatible with the open agentskills.io standard. | D5: Distinct from the Tool/MCP layer (TM-07's Tool Gateway = built-in capabilities like web search/TTS/browser automation). Skills are learned procedures layered on top of whatever tools exist — don't conflate the two rows. | E5: Understood, not yet used
A6: Storage & directory structure | B6: Where skills physically live on hermes-vps. | C6: ~/.hermes/skills/<category>/<skill-name>/ containing SKILL.md (required) plus optional references/, templates/, scripts/, examples/, assets/ subfolders. | D6: Primary source of truth is the filesystem, not a database — matches the 'everything on the VPS, self-sufficient' architecture rule already set for this project. | E6: Understood, not yet used
A7: Discovery & invocation | B7: How the agent finds and loads a skill without burning context on all of them upfront. | C7: 3-level progressive disclosure: skills_list() (~3k tokens, metadata only) -> skill_view(name) (full SKILL.md) -> skill_view(name, path) (one reference file). Invoked via /skill-name slash commands (stackable: /skill1 /skill2 instruction), or picked up from natural conversation. | D7: Token-cheap by design — matches the economic-router priority already set for this project (LLM-as-judge router logged 2026-10-03). | E7: Understood, not yet used
A8: Bundled vs optional skills | B8: Counted directly against the live NousResearch/hermes-agent source tree (GitHub API, 2026-10-05) after an earlier pass here cited a wrong '166 (87+79)' figure from a secondary blog summary. | C8: VERIFIED 2026-10-05 via github.com/NousResearch/hermes-agent: 58 bundled skills across 12 categories (apple, autonomous-ai-agents, creative, devops, email, media, note-taking, productivity, research, social-media, software-development, web) + 145 optional skills across 22 categories (adds blockchain, communication, data-science, dogfood, finance, gaming, health, mcp, migration, mlops, payments, security, smart-home, web-development, yuanbao to the bundled list — the original optional-category list here had missed 11 of these entirely). `hermes skills opt-out` behavior for bundled seeding still unconfirmed from docs alone. | D8: Counts will keep moving (repo had 48k+ commits, pushed within the last hour at check time) — treat any specific number as a snapshot, not a constant. Re-count with `hermes skills list` once hermes-vps exists rather than trusting this or any future doc/blog figure at face value. | E8: Corrected against primary source 2026-10-05 — counts were wrong, categories now complete
A9: Self-authored skill creation | B9: How the agent writes its *own* new skills during use — the actual 'self-improvement via skills' loop. | C9: Agent calls skill_manage(action=create/patch/patch-with-content/delete/write_file/remove_file). Docs describe it recording a new reusable skill after completing a complex task (~5+ tool calls) with zero human authoring. Writes can be gated: `skills.write_approval: true` stages them under ~/.hermes/pending/skills/ for human review instead of applying immediately. | D9: Recommend `write_approval: true` at least initially — same 'review before trust' posture already applied to the unofficial Obscura plugin. Revisit once the agent's judgment on what's worth turning into a skill has a track record. | E9: Not yet configured
A10: Security & sandboxing | B10: What stops an installed or self-written skill from doing something malicious. | C10: Hub-installed skills get scanned for data exfiltration, prompt injection, destructive commands, and supply-chain signals; an optional NVIDIA SkillEvaluator Tier-1 scan adds PII detection. Project-local skills (.hermes/skills/ inside a git repo) get the same scanner before entering the index, with dangerous findings quarantined. Skills can declare required_environment_variables, which Hermes requests and passes through to execute_code/terminal sandboxes automatically. | D10: The required_environment_variables mechanism is a second place secrets can leak outside the vault (05_Secrets_Vault) if a skill mishandles them — worth a Security Hardening row once any skill actually declares one. | E10: Understood, no mitigating row logged yet
A11: Bundled categories relevant here | B11: Which of the 12 bundled categories actually matter for this project's shape. | C11: Autonomous AI Agents (delegate to Claude Code / Codex / OpenCode, computer automation, Hermes-orchestrates-Hermes), DevOps (lifecycle review, Kanban handoff verification), Productivity (Google Workspace, Office docs, meeting action items), Research (arXiv, competitor monitoring, citation grounding), Email (IMAP/SMTP via Himalaya CLI). | D11: 'Autonomous AI Agents' directly overlaps the Codex-as-thinking-tier routing decision already locked (03_Model_Routing_Resilience) — check this category first once hermes-vps exists, it may already implement part of that routing instead of needing custom work. | E11: Not yet cross-checked against 03_Model_Routing_Resilience
A12: Optional categories relevant here | B12: Which of the 23 optional categories are worth installing given this project's actual needs. | C12: smart-home (Philips Hue via OpenHue CLI — only relevant if Hue exists on the home network, unconfirmed), security (1Password, Sherlock account discovery, data-broker removal), devops (Docker container mgmt, SSH tunneling, RSS/JSON API monitoring — overlaps the Docker terminal backend already locked), mcp (build/deploy custom MCP servers, OAuth handling — overlaps the 4 custom MCP servers already in 04_Tool_MCP_Layer), data-science (Jupyter notebook execution). Also present but not yet assessed for relevance: blockchain, communication, data-science (separate from the devops/mcp ones already named), dogfood, finance, gaming, health, migration, payments, web-development, yuanbao — original pass missed these 11 categories entirely (corrected 2026-10-05). | D12: mcp and devops optional-skill categories are the two with real near-term relevance — they overlap tooling this project is already hand-building (TM-01 through TM-14). Worth checking whether the optional skill replaces hand-rolled work before building more MCP servers manually. | E12: Candidates identified, none installed — needs explicit go-ahead, this is still discovery
A13: Open question for next session | B13: What this discovery pass did NOT resolve. | C13: Whether any home-network device (Hue, etc.) actually exists to make smart-home skills relevant; whether bundled skills already cover gaps currently tracked as custom work in 01-15 tabs; exact behavior of hermes skills opt-out (full vs partial). | D13: Answer by running `hermes skills list` and `hermes skills search <keyword>` directly against hermes-vps once it exists, rather than guessing further from docs alone. | E13: Open

Sheet D4_Crons_System
A1: Discovery — Crons System (Five Pillars: Crons)
A2: Researched 2026-10-05, verified against primary source (github.com/NousResearch/hermes-agent cron/AGENTS.md, cron/scheduler_provider.py, website/docs/user-guide/features/cron.md), not secondary summaries. Scope per explicit user instruction: confirm the SYSTEM CAN schedule work, not design actual cron jobs -- no jobs created, still discovery.
A4: Topic | B4: What it is | C4: Options found | D4: Recommendation / dependency detail | E4: Status
A5: What cron is | B5: Hermes's built-in scheduler -- the pillar answering 'can it work without being summoned.' | C5: cron/jobs.py (job store) + cron/scheduler.py (tick loop) + scheduler_*.py siblings. Users: `hermes cron <verb>` or `/cron`. Agents: the `cronjob` tool. A genuinely mature subsystem -- the internal dev notes (cron/AGENTS.md) cite specific hardening fixes by bug number (#107485, #114587, #122222), not a thin wrapper. | D5: Treat as production-grade, not experimental -- the only EXPERIMENTAL-labeled piece is the pluggable external-provider interface (scheduler_provider.py), not the builtin scheduler itself. | E5: Verified real
A6: Hard prerequisite: persistent gateway | B6: Cron jobs are ticked by a loop that runs INSIDE the gateway process -- no gateway process running means no cron ever fires. | C6: `hermes gateway install` (user service) / `sudo hermes gateway install --system` (boot-time) / `hermes gateway` (foreground). The ticker is a SupervisedTickerThread started on gateway boot. One host gateway process ticks EVERY served profile's store -- relevant if CR-15 (sister's separate Hermes) ever shares infra. | D6: ALREADY SATISFIED on hermes-vps -- cross-ref 01_Core_Runtime CR-03 'hermes-gateway running persistently', status Done, evidence hermes-gateway.service (systemd). This is the one thing this pillar actually needed built, and it already is. | E6: Done (via CR-03) -- confirmed, not re-tracked here
A7: Schedule formats | B7: What a job's timing can be expressed as. | C7: Relative one-shot (`in 30m`, `in 2h`, `in 1d`); recurring interval (`every 30m`, `every 2h`); natural recurring (`every monday 9am`, `weekdays at 9am`, `daily at 7am`); 5-field cron expressions (`0 9 * * *`); ISO one-shot timestamps. | D7: No decision needed here -- this is a format reference for whenever a real job gets created, not a choice to lock in now. | E7: Understood, not used
A8: Per-job capabilities | B8: What a single cron job definition can actually do, beyond 'run a prompt on a timer.' | C8: Fields: `skills` (attach specific skills to the run), `model`/`provider` override, `script` (pre-run data-collection script piped into the prompt), `--no-agent` (script output delivered verbatim, skips the LLM entirely -- a watchdog pattern), `context_from` (chain job A's last output into job B's prompt), `workdir` (loads that directory's AGENTS.md/CLAUDE.md), multi-platform delivery targets. | D8: The --no-agent script-only mode is the right fit for cheap health-check-style jobs (e.g. monitoring hermes-vps resource headroom, CR-12) once that's wanted -- no LLM cost, verbatim script stdout delivered only when non-empty. | E8: Understood, not used
A9: Delivery | B9: Where a job's output actually goes once it runs. | C9: `origin` (back to the creating chat, platform default), `local` (~/.hermes/cron/output/, CLI default), `telegram`/`telegram:<chat_id>`, `discord`, `slack`, `email`, `sms`, `all` (every connected home channel), comma-separated multiple targets, `bot-chat`. | D9: Telegram delivery directly reuses the IA-05 gateway decision already locked -- no new dependency once that bot token exists. | E9: Understood, not used
A10: Config keys | B10: What config.yaml controls for the whole cron subsystem. | C10: `cron.model`/`model_provider` (default for unpinned jobs), `preflight` (validate before run), `wrap_response`, `catch_up_missed` (re-run once on restart if a fire was missed), `failure_nudge_threshold`, `retry_unreachable` (auto-retry transient network errors at 5/15/30min), `failure_repeat_alert_hours`, `allow_agent_scheduling` (default false -- cron-run sessions cannot recursively create more cron jobs unless this is on), `max_parallel_jobs` (default 10), `script_timeout_seconds` (default 3600), `cron.provider` (external scheduler override, defaults to builtin). | D10: `allow_agent_scheduling: false` (the default) is the right posture to keep -- matches the same 'review before autonomy' stance already applied to skill write_approval and the Obscura plugin. | E10: Understood, not configured
A11: Storage | B11: Where cron state physically lives. | C11: Job definitions: ~/.hermes/cron/jobs.json. Run outputs: ~/.hermes/cron/output/{job_id}/{timestamp}.md. Execution history: ~/.hermes/cron/executions.db. | D11: All on-box, no external dependency -- consistent with the hermes-vps self-sufficiency rule. | E11: Understood, not used
A12: Hardening (why this isn't a toy scheduler) | B12: Failure modes the system already guards against, per cron/AGENTS.md. | C12: Inactivity watchdog on cron sessions (default 600s idle via HERMES_CRON_TIMEOUT, separate from script_timeout_seconds); catch-up window for missed one-shots (120s grace); per-home tick lock file prevents duplicate ticks across processes; restart-safe external worker processes under systemd; at-most-once accounting across a mid-run crash (next_run_at advances before dispatch). | D12: No action needed -- flagging so a future session doesn't assume this needs building when it's already handled. | E12: Verified real, nothing to build
A13: Cross-pillar interaction: memory does NOT run during cron | B13: A real gotcha found while verifying, not mentioned in any secondary source. | C13: Direct quote, cron/AGENTS.md: 'Cron sessions pass skip_memory=True; memory providers intentionally do not run during cron.' | D13: Worth a Notes/Next-Action flag on IM-05 (Hindsight) once memory is actually deployed: a cron job's output won't be written to or informed by extended memory unless something explicitly changes that. Not a blocker, just don't assume cron jobs get the same memory context an interactive chat gets. | E13: Flagged — see 02_Identity_Memory IM-05
A14: Adjacent but out of scope: Kanban | B14: A related multi-agent work-queue system documented in the same source file as cron, easy to conflate with it. | C14: SQLite-backed board for multiple profiles/workers to collaborate (hermes kanban <verb>). Separate feature, separate toolset, not part of the Five Pillars. | D14: Noting its existence only so it isn't mistaken for part of Crons later -- not pursued in this discovery pass. | E14: Noted, not researched

Sheet D5_Self_Improvement
A1: Discovery — Self-Improvement System (Five Pillars: Self-Improvement)
A2: Researched 2026-10-05, verified against primary source (github.com/NousResearch/hermes-agent agent/background_review.py, agent/curator.py, agent/AGENTS.md, skills/AGENTS.md, and the official memory.md / curator.md docs) before writing anything here. Last of the Five Pillars -- none of Memory/Soul/Skills/Crons/Self-Improvement remain unresearched after this tab.
A4: Topic | B4: What it is | C4: Options found | D4: Recommendation / dependency detail | E4: Status
A5: What self-improvement actually is | B5: Not one feature -- three distinct mechanisms working together: a per-turn background review, a skill lifecycle manager (Curator), and free cross-session search. | C5: agent/background_review.py (+ review_engine.py, review_idle_queue.py), agent/curator.py (+ curator_backup.py), tools/session_search_tool.py. All three confirmed real and substantial in source, not a marketing label over something thin. | D5: The 'work -> learn -> save to memory/skills -> search past sessions' framing from the earlier session summary is directionally right but understates it -- there's a whole skill-lifecycle subsystem (Curator) that framing didn't mention at all. | E5: Verified real
A6: Background review (the actual learning loop) | B6: After every conversation turn, Hermes forks itself to ask 'should anything here be saved as a memory or a skill' -- and writes directly if so. | C6: Direct quote, agent/background_review.py: 'Background memory/skill review — fork the agent to evaluate the turn... asks "should any skill/memory be saved or updated?". Writes go straight to the memory + skill stores; the main conversation and prompt cache are never touched.' Runs as a daemon thread, inherits the parent's live runtime (provider/model/credentials/cached system prompt) so it hits the same prompt-cache prefix, and runs under a restricted tool whitelist. | D6: This is the mechanism that would actually act on this project's 'memory upkeep is Claude's job, not the user's' ground rule, once ported to Hermes itself -- it's architecturally the same idea (passive capture, not waiting to be asked), already built-in rather than something to design from scratch. | E6: Verified real
A7: Background review: model routing | B7: Which model does the per-turn review -- doesn't have to be the expensive main model. | C7: Config: `auxiliary.background_review.provider` / `.model` (e.g. route to a cheaper model like google/gemini-3-flash via openrouter), `.max_input_tokens` (cost cap), `.defer` (e.g. `auto` -- queues the review instead of running it immediately when a local GPU model is busy). | D7: Directly overlaps the local-model-as-tool-tier / Codex-as-thinking-tier routing decision already made for this project (03_Model_Routing_Resilience) and the economic LLM-as-judge router. Background review is a THIRD consumer of that same routing logic, not a new concept -- check whether it can just plug into the existing router instead of getting separately configured. | E7: Needs cross-check against 03_Model_Routing_Resilience once hermes-vps exists
A8: Background review: approval gating | B8: Whether a human reviews what gets auto-saved, same question already asked for Skills (write_approval). | C8: `memory.write_approval` (default false) -- when true, background writes stage via `/memory pending` / `/memory approve` instead of applying directly; foreground (in-conversation) writes prompt inline instead. | D8: Recommend `write_approval: true` initially -- same 'review before trust' posture already applied to skills.write_approval and the Obscura plugin. This is the memory-side twin of that same decision, should probably be set together, not separately. | E8: Not yet configured
A9: Skill Curator (lifecycle management) | B9: Background maintenance that keeps self-authored skills from piling up as stale cruft -- the 'does it get better with use, or just bigger' question. | C9: Deterministic auto-transitions (no LLM cost): active -> stale (14d unused, configurable via `stale_after_days`) -> archived (30d, `archive_after_days`) -> `~/.hermes/skills/.archive/` (restorable, never hard-deleted). Optional LLM consolidation pass (`curator.consolidate`, off by default, token cost) can merge overlapping skills or patch drift. Runs on an inactivity schedule (default 7 days since last run + 2h agent idle, `min_idle_hours`), not on a cron timer. Pre-run tar.gz backups + rollback. CLI: `hermes curator status|run|pause|resume|pin|unpin|archive|restore|prune|backup|rollback`. | D9: CONFIRMED (source, not docs page): Curator only ever touches skills with `created_by: "agent"` -- bundled and hub-installed skills are permanently off-limits to it, even with `prune_builtins` on for the deterministic walk. This is a real safety boundary worth knowing before assuming Curator could ever 'clean up' something you installed yourself. | E9: Verified real
A10: Cross-session search | B10: How the agent finds something from a conversation weeks ago without it being in the 2,200-char MEMORY.md snapshot. | C10: tools/session_search_tool.py queries `~/.hermes/state.db` (SQLite, FTS5 full-text index) across all CLI and messaging sessions. Returns actual past messages, no summarization/truncation, ~20ms, zero LLM cost. | D10: This plus MEMORY.md are complementary, not redundant: MEMORY.md is the always-loaded curated snapshot (~1,300 tokens/session), session_search is free on-demand lookup for anything NOT curated into that snapshot. Matches the IM-07 retention policy already found (facts persisted aggressively, curation forces a filter) -- session_search is the safety net for what curation leaves out. | E10: Verified real
A11: Learning visibility (Desktop only) | B11: A way for a human to actually SEE what the agent has learned, not just trust it happened. | C11: agent/learning_graph.py assembles a graph for the Desktop app: skill nodes (agent-created/used) + MEMORY.md/USER.md chunks as nodes, linked via declared `related_skills` and lexical overlap. Visualization only, not a reasoning mechanism. | D11: Relevant to 09_Observability ('health signals a human can actually see') once the Desktop interface (08_Interfaces_Access) is in use -- this is a built-in answer to 'how do I know self-improvement is actually doing anything,' not something to build custom. | E11: Verified real, Desktop-dependent
A12: Open question for next session | B12: What this pass did NOT resolve. | C12: Whether background_review still fires during a cron-run session (cron confirmed to skip memory PROVIDERS via skip_memory=True, per D4 -- unconfirmed whether the separate background_review/Curator mechanisms are also suppressed, since they write to MEMORY.md/skills directly rather than through a memory provider). Whether memory.write_approval and skills.write_approval need to be set together or are independent toggles in practice. | D12: Answer by reading agent/review_engine.py's cron-session handling directly, or by testing once hermes-vps exists -- don't assume either way from the docs alone. | E12: Open

Sheet D6_Web_Dashboard
A1: Discovery — Web Dashboard (every sidebar menu, page by page)
A2: Researched 2026-10-05 after the user shared live dashboard screenshots (hermes-vps's own web UI, qwen3-vl:4b-hermes-instruct, 58 skills/14 categories, 4 MCP, v0.21.5 -- matches 01_Core_Runtime exactly). Verified against primary source: website/docs/user-guide/features/web-dashboard.md + credential-vault.md + credential-pools.md + checkpoints-and-rollback.md + profiles.md + messaging/*.md. Cross-references into 01-15 tabs are noted inline; this tab stays the reference copy.
A4: Dashboard page | B4: What it actually does | C4: Primary-source detail | D4: Cross-reference / why it matters | E4: Status
A5: Status (landing page) | B5: Agent version, gateway status, active sessions, recent session summaries, resource-pressure warnings. Auto-refreshes every 5s. | C5: Confirmed in web-dashboard.md. Matches exactly what the shared screenshot showed (v0.21.5, Gateway Status: Running, 0 active sessions). | D5: Live-confirms CR-02/CR-03 (01_Core_Runtime) are actually Done, not just believed done. | E5: Verified, matches live instance
A6: Chat | B6: Full TUI embedded in-browser via WebSocket + PTY -- slash commands, model picker, tool-call visualization, session sidebar, workspace picker. Identical to CLI. | C6: web-dashboard.md. | D6: This IS the IA-01/IA-02 'Web UI' row in 08_Interfaces_Access -- already exists and is what the screenshots show, not something still to build. | E6: Verified, live
A7: Config | B7: Form-based editor for config.yaml -- 150+ fields across tabs (model, terminal, display, agent, delegation, memory, approvals, etc.). Save / reset-to-defaults / export-as-JSON / import. | C7: web-dashboard.md: 'A form-based editor for config.yaml.' Separately, configuration.md (CLI reference) never mentions a UI, describes only hermes config edit/set/get -- the dashboard form is additive on top of the CLI, not documented in the same place. | D7: Directly relevant to CR-13 (comment-preserving edits) and CR-14 (staged config changes) in 01_Core_Runtime -- a structured form editor may be a simpler answer than hand-rolling ruamel.yaml. Whether it preserves YAML comments on the fields it DOESN'T toutouch is unconfirmed -- check before relying on it for CR-13. | E7: New finding, not yet tested
A8: API Keys (sidebar: 'KEYS') | B8: Manage .env credentials grouped by category (LLM providers, tool integrations, messaging, agent settings). Status/description/signup links/delete per entry. NOT encrypted-at-rest -- this is .env management, not the Credential Vault (separate feature, see below). | C8: web-dashboard.md. | D8: IMPORTANT DISTINCTION found this session: this is a different thing from both (a) this project's own Postgres catalog vault (SV-01, already Done, external) and (b) Hermes's own local Credential Vault (next row). Three separate 'vault-shaped' things now exist -- don't conflate them. | E8: New finding, clarifies SV-01 scope
A9: Credential Vault (NOT a sidebar item seen yet -- Desktop Settings or `hermes vault`) | B9: A LOCAL, Fernet-encrypted store at ~/.hermes/vault/ (0600 perms) for browser-fill website passwords specifically -- 'the model never sees them,' origin-bound auto-fill. Different purpose from API Keys above (that's provider/tool credentials; this is login passwords for sites the browser-automation tool fills in). | C9: credential-vault.md, directly quoted: 'passwords are encrypted on this machine and injected straight into the page; the model never sees them.' CLI: hermes vault list/add/rm/sources. Desktop: Settings -> Passwords & Logins. | D9: Relevant to TM-14 (Obscura browser automation, locked in) -- this is likely the mechanism that would hold any login credentials Obscura needs to fill forms with. Not yet connected to anything in this workbook. | E9: New finding, unused
A10: Credential Pools | B10: Register MULTIPLE API keys/OAuth tokens for the SAME provider; Hermes auto-rotates on rate-limit/billing errors. Strategies: fill_first (default), round_robin, least_used, random. Tried BEFORE fallback providers kick in. | C10: credential-pools.md. CLI: hermes auth add <provider> --api-key ..., hermes auth list. Config: credential_pool_strategies: {provider: strategy}. | D10: Distinct from and complementary to MR-13 (Vultr/DeepSeek fallback, already locked in 03_Model_Routing_Resilience) -- pools rotate within one provider, fallback switches provider entirely. Pools are a cheap way to add resilience to Anthropic/OpenRouter calls specifically if ever rate-limited, no new concept needed, just more keys for the same provider. | E10: New finding, not needed yet
A11: Sessions | B11: Browse/search all conversations (full-text, filter Chats/Automation/All), expand to see message history, rename, export as JSON, delete, bulk-prune. | C11: web-dashboard.md. Backed by the same ~/.hermes/state.db FTS5 index as session_search (see D5_Self_Improvement). | D11: Export-as-JSON is a real, built-in answer to IM-06 (02_Identity_Memory, 'Hermes runtime-memory backup') -- don't build a custom exporter, this already exists. | E11: New finding, relevant to IM-06
A12: Logs | B12: Agent/gateway/error logs, filter by level (DEBUG-ERROR) and component, live-tail. | C12: web-dashboard.md. | D12: Relevant to 09_Observability ('health signals a human can actually see') -- likely satisfies part of that tab once reviewed in detail (not yet cross-checked row by row). | E12: New finding, not cross-checked against 09_Observability yet
A13: Analytics | B13: Token counts, cache hit rates, estimated costs, daily breakdowns, per-model stats, charts, for 7/30/90-day windows. | C13: web-dashboard.md. | D13: This is a BUILT-IN answer to CS-05 (11_Cost_Subscriptions, 'Total monthly Hermes cost rollup', the tab the user already called 'the actual point of the project') -- worth checking before building any custom cost tracking. | E13: New finding, directly relevant to CS-05
A14: Profiles | B14: Create/manage isolated Hermes instances (own config/skills/sessions/memory/cron). Shows model, skill count, gateway state. Supports clone / clone-all / clone-from / export-import (API keys stripped on export). | C14: profiles.md, directly quoted: 'Never point two agent processes at the same profile... two writers on one home compound each other's state.' Profile = separate HERMES_HOME directory; NOT a filesystem sandbox (full user permissions still apply). | D14: Directly validates CR-15 (sister's Hermes, full separation already decided) -- confirms that was the right call, sharing a profile would have actively corrupted both agents' state. profile export/import (keys stripped) could cheaply replicate config/personality to her instance without hand-copying files. | E14: Verified, validates CR-15
A15: Skills | B15: Browse/search/toggle installed skills + toolsets by name/description/category; separate hub browser for installing/updating. | C15: web-dashboard.md. | D15: Same system as D3_Skills_System -- this is the GUI for what D3 researched via source/API. No new facts, just confirms a UI exists. | E15: Confirms D3, no new facts
... A26: Kanban (plugin, sidebar under Plugins) | B26: Already covered in D4_Crons_System as 'adjacent but out of scope' -- cross-referencing here since it's visible in the same sidebar screenshot. | C26: See D4_Crons_System for detail (SQLite-backed multi-agent work queue, separate from Crons). | D26: No new information -- just confirming the sidebar item matches what D4 already found. | E26: Already covered in D4

Sheet D7_Setup_Execution_Workflow
A1: Discovery — Setup Execution Workflow (sequenced runbook, not yet run)
A2: Source: a community guide (r/hermesagent, 'Complete Hermes Agent Setup Guide', u/smolpotat0_x, posted ~2026-03, i.e. ~7 months stale against a project doing 48k+ commits) -- user supplied as PDF 2026-10-05. EVERY command below was spot-checked against current github.com/NousResearch/hermes-agent source (hermes_cli/gateway.py, cron.py, tools/skills_hub.py, doctor.py, pairing.py) before being kept, given the staleness risk. This is a REFERENCE RUNBOOK for the eventual execution phase -- nothing here has been run. Steps already Done on hermes-vps are marked accordingly.
A4: Step | B4: Action | C4: Command(s) -- verified against current source | D4: Status on hermes-vps / notes | E4: Verification
A5: 1. Prerequisites | B5: OS/shell/git/internet check; Windows needs WSL2 (native Windows unsupported per the guide). | C5: No command -- environment check only. | D5: N/A -- hermes-vps is Linux. Relevant instead to 07_Local_Inference's Windows build (ik_llama.cpp) on w_workstation, which already has its own separate dependency list in D2_Providers_And_Deps. | E5: Not re-verified, low-risk claim
A6: 2. Pick an LLM API key / provider | B6: Hermes needs at least one provider key to generate responses even before any local model exists. | C6: Guide lists OpenRouter, MiniMax, Nous Portal, OpenAI, Anthropic, GLM, Kimi as options; recommends OpenRouter for free credits. | D6: Already superseded by this project's own decisions: Codex/ChatGPT Plus is the 'thinking tier' (CS-01, Done), DeepSeek-V4-Flash via Vultr is the cloud fallback (MR-13, locked). No need to follow the guide's generic recommendation. | E6: Superseded by existing decisions
A7: 3. Install | B7: Run the official installer script. | C7: curl -fsSL https://raw.githubusercontent.com/NousResearch/hermes-agent/main/scripts/install.sh | bash (guide's command was truncated in the PDF, reconstructed from the known install.sh path already confirmed real in CR-02's migration). | D7: ALREADY DONE -- CR-02 (01_Core_Runtime) is Done, migrated 2026-09-29 to this exact supported install.sh/git channel, currently v0.21.5+. | E7: Already satisfied (CR-02)
A8: 4. Reload shell + verify | B8: Confirm the hermes binary is on PATH. | C8: source ~/.bashrc; hermes --version | D8: Already satisfied -- live dashboard screenshot shows v0.21.5 running. | E8: Confirmed live
A9: 5. Initial setup wizard OR manual config | B9: Either the interactive wizard, or direct config commands. | C9: hermes setup (interactive: provider, API key, model, tools, messaging) -- OR manually: hermes config set <KEY> <VAL>, hermes model, hermes tools. | D9: Partially done piecemeal (CR-02 install, but the wizard itself and a deliberate model/tools pass not confirmed run) -- worth running `hermes config` to see current state before assuming anything. | E9: hermes config set/edit confirmed against current configuration.md
A10: 6. config.yaml key structure | B10: What the file actually looks like once configured. | C10: model.default, model.provider, model.base_url, agent.max_turns, agent.reasoning_effort, toolsets, display.personality, display.compact, terminal.timeout, memory.memory_enabled. | D10: Directly relevant to CR-13/CR-14 (comment-preserving/staged edits) -- this is the exact key set any editing approach (CLI, dashboard Config form, or hand-edit) needs to handle correctly. | E10: Matches current configuration.md reference table
A11: 7. Secrets via .env | B11: Sensitive values stay out of config.yaml. | C11: ~/.hermes/.env -- OPENROUTER_API_KEY, MINIMAX_API_KEY, TELEGRAM_BOT_TOKEN, DISCORD_BOT_TOKEN, HASS_TOKEN, HASS_URL, etc. | D11: Relevant to SV-09 (05_Secrets_Vault, 'Vultr inference key removed from config.yaml plaintext', Not Started) -- confirms the intended pattern is .env, not inline config.yaml values. | E11: Matches current docs
A12: 8. Gateway + messaging platforms | B12: Connect Telegram/Discord/WhatsApp/Slack/Signal/Email so Hermes is reachable outside the terminal. | C12: hermes gateway setup (interactive per-platform) -- Telegram: message @BotFather, /newbot, copy token, hermes gateway setup. Discord: Developer Portal, create bot, copy token. WhatsApp: QR pairing. Then hermes gateway start (background service) / hermes gateway run (foreground debug) / hermes gateway status. | D12: ALREADY PARTIALLY DONE -- CR-03 (gateway running persistently, systemd, Done) covers the service itself; IA-05 (Telegram channel, Partial) still needs the actual BotFather token created and run through this exact flow. | E12: gateway start/run/status/install all confirmed present in current hermes_cli/gateway.py
A13: 9. Tools and toolsets | B13: See and enable capability categories. | C13: hermes tools (list available) -- categories seen: Web, Code, File, Vision, Memory, Communication (telegram_send, discord_send, email), Home (home_assistant: lights/switches/climate), Research (arxiv_search, duckduckgo_search). hermes tools --list / --set cli / --set all for toolset bundles. | D13: The 'Home' toolset category (home_assistant) independently confirms the Home Assistant integration D6_Web_Dashboard already flagged as an open question -- still unconfirmed whether HA runs on the home network. | E13: Category names consistent with D3/D6 findings
A14: 10. Personality | B14: Quick personality presets, distinct from full SOUL.md authoring. | C14: hermes config set display.personality <helpful|creative|teacher|kawaii|pirate|noir>. | D14: Lighter-weight than IM-01 (SOUL.md committed, Not Started) -- a preset is not a substitute for the actual SOUL.md drafted in this project's earlier Memory/Soul discovery, just a faster default if SOUL.md isn't ready yet. | E14: Not independently re-verified, low risk
A15: 11. Skills | B15: Browse/install reusable procedures. | C15: hermes skills (browse), hermes skills search <query>, hermes skills install <name>, hermes skills remove <name>. | D15: Matches D3_Skills_System's `hermes skills list`/`install`/`search` findings closely enough (browse vs list is cosmetic) -- no new facts, just confirms the guide and the source-verified D3 findings agree. | E15: Consistent with D3, both from source
... A22: Noted, not recommended: third-party one-click deployers | B22: A commenter built 'hermify.io' -- Docker image + Tailscale + Cloudflare Tunnel, <60s to a live Hermes. | C22: Unofficial, third-party, not from Nous Research. Would touch credentials and networking decisions this project has already made independently (Vultr-preferred, WireGuard not Tailscale, self-sufficiency rule). | D22: Same risk class as the Obscura browser-automation plugin (unofficial, accepted knowingly there) -- NOT recommended here since it would duplicate/override infrastructure decisions already locked, not fill a gap. | E22: Noted only, not pursued

Sheet D8_Advanced_Reference
A1: Discovery — Advanced Reference (Practitioner's Reference PDF + hermesbible.com)
A2: Researched 2026-10-05. Two sources: a 255-page community practitioner reference (user-supplied PDF, every claim footnoted to upstream docs/source) and hermesbible.com's llms-full.txt (bulk-downloadable, 169 official-docs pages + ~40 unique community 'flows'). Corrections to earlier D3-D7 findings are called out explicitly. Cross-references into 01-15 tabs noted inline.
A4: Topic | B4: What it is | C4: Detail | D4: Cross-reference / why it matters | E4: Status
A5: CORRECTION: TM-07 Nous Tool Gateway | B5: 04_Tool_MCP_Layer TM-07 described this as '5 sandboxed exec backends' -- that was wrong, conflating two separate systems. | C5: The real Tool Gateway is 4 tools only (web_search/Firecrawl, image_gen/FAL, TTS/OpenAI, browser automation/Browser Use), opt-in per-tool via `use_gateway: true`, and requires a PAID Nous Portal subscription (OAuth login via `hermes model` or `hermes setup --portal`) -- it does not work on the free tier for these 4 tools specifically. The '5 exec backends' is actually the terminal tool's backend list, which is really 7: local, docker (locked in, CR-17), ssh, singularity, modal, daytona, vercel_sandbox. | D5: Given Obscura (browser), and existing web-search/TTS providers are already locked in, this Gateway likely isn't worth a paid subscription just for it. Fix TM-07's description either way. SSH backend is worth knowing about as a MORE isolated alternative to Docker -- docs' own words: 'the agent can't modify its own code.' | E5: Correction -- needs TM-07 text fixed
A6: GEPA: offline skill evolution | B6: A fourth self-improvement mechanism, separate from the three already found in D5 (background review, Curator, session search). | C6: Lives in a companion repo (NousResearch/hermes-agent-self-evolution, ICLR 2026 Oral paper, MIT licensed), not the runtime itself. Addresses a known weakness: the in-agent loop tends toward self-congratulation (thinks it did well even when it didn't). GEPA reads execution traces to understand WHY things failed, proposes candidate skill variants via genetic-pareto search, gates them on full test suite pass + size/caching constraints, and ships the best variant as a PR against the repo -- never a direct commit. No GPU required, ~$2-10/run. | D6: Not needed for initial setup -- an optimization to reach for later, once real usage history exists to feed it. Add to D5_Self_Improvement as the fourth mechanism. | E6: New finding, not needed yet
A7: hermes egress + Bitwarden: credential protection stack | B7: Fully explains the `hermes egress` command found earlier but not understood -- a real, available (Docker-backend-only) defense against a prompt-injected agent stealing its own API keys. | C7: Two composable layers: (1) Bitwarden Secrets Manager centralizes credentials (one bootstrap token in .env, everything else in the vault, instant fleet-wide revocation) via `hermes secrets bitwarden setup`. (2) iron-proxy (`hermes egress`) gives sandboxed commands OPAQUE proxy tokens instead of real keys -- the real credential is swapped in only at the network boundary, so a compromised sandbox walks away with tokens useless outside the proxy. `hermes egress setup --from-bitwarden` chains the two. Also blocks SSRF to cloud metadata (169.254.169.254) by default. Docker-only for now (matches CR-17 exactly). | D7: OPEN QUESTION (not resolved): does iron-proxy require Bitwarden specifically, or could `--from-bitwarden` have an equivalent pulling from the existing catalog Postgres vault instead? Don't adopt Bitwarden as a new standing system without checking this first -- would otherwise duplicate infrastructure. See SV-16. | E7: New finding, real capability, adoption path unclear
A8: Docker backend: container_memory default is wrong for this VPS | B8: A concrete gotcha for CR-17 (Docker terminal backend, already locked in). | C8: `terminal.container_memory` defaults to 5120 (5GB) -- hermes-vps has 4GB total RAM. Must be explicitly set lower in config.yaml or Docker-backed commands risk OOM. | D8: Direct action item for whoever executes CR-17's remaining config -- not optional, the default will not work on this box. | E8: Actionable gotcha, not yet applied
A9: Local model tool-calling: per-server flag requirements | B9: Tool calls silently render as unparseable text instead of executing unless the local inference server is started with the right flag -- directly relevant to LI-03/LI-04 (ik_llama.cpp locked in, Partial). | C9: llama.cpp/llama-server: needs `--jinja` or tool calls fail silently. vLLM: `--enable-auto-tool-choice --tool-call-parser hermes`. SGLang: `--tool-call-parser qwen`. Ollama: tool-calling is on by default but verify with `ollama show <model>`. LM Studio: needs v0.3.6+ with native tool-call support, and GGUF context-length metadata is often wrong (set manually in UI, min 16384, prefer 32768). | D9: ik_llama.cpp's own equivalent of --jinja has NOT been specifically verified (it's a fork, conventions may differ) -- check this before assuming tool-calling will just work once the runtime is up. Directly actionable for LI-07 benchmarking. | E9: Actionable gotcha, fork-specific flag unverified
A10: Context length must usually be set explicitly | B10: Directly closes LI-06 (07_Local_Inference, 'Context window aligned with Hermes's floor', Not Started) -- now known exactly what to do. | C10: Hermes auto-detects context length from the server's /v1/models endpoint, but many local servers (Ollama especially) report wrong/low defaults (2048 is a common failure symptom). Fix: set `model.context_length` explicitly in config.yaml. Hermes's own stated minimum is 64k context for full feature support (voice, etc per one community flow). Ollama-specific gotcha: `ollama show` reports the model's MAXIMUM context, not the effective num_ctx actually configured -- these can differ. | D10: LI-06 can move to Done as soon as this explicit config value is set and verified against the actual runtime's real context window, not assumed from a model card. | E10: Actionable, directly closes LI-06
A11: Security hardening is substantially built-in already (v0.13.0-v0.21.0) | B11: Directly relevant to 12_Security_Hardening -- much of what might be assumed to need custom work is already shipped and on by default, contingent on being current (CR-02 already confirms v0.21.5+). | C11: v0.21.0 made writes to protected agent-instruction files (AGENTS.md/CLAUDE.md/SOUL.md/.cursorrules/skills/memory) ALWAYS require approval by default (`security.protected_instruction_files: true`) -- closes the exact 'prompt-injected agent rewrites its own standing orders' vector. Browser tool has a built-in SSRF floor blocking cloud metadata endpoints. Supply-chain advisory scanning runs during install and on every plugin/skill install. Secret redaction is default-on for logs and `hermes debug share`. A REAL precedent exists for the unofficial-plugin risk already accepted for Obscura: the Blender MCP catalog entry was removed after an actual upstream supply-chain compromise. | D11: Action for SH-04/SH-06/SH-07: mostly a VERIFICATION task (confirm these defaults weren't disabled) rather than a build task. `hermes doctor` and `hermes security audit` (OSV.dev scan of venv/plugins/MCP servers) are the two commands to run first. | E11: Mostly already satisfied -- needs verification, not building
A12: hermes import-agent | B12: A real, literal mechanism for this project's own stated end-goal (CLAUDE.md: 'this whole maintenance role eventually moves into Hermes itself'). | C12: Imports an existing Claude Code (~/.claude) or Codex CLI (~/.codex) setup directly into a Hermes profile. | D12: Directly relevant to GV-02 (13_Governance_Change_Mgmt, 'Claude-Code-as-bootstrap sunset plan', Not Started) -- this may BE the sunset mechanism, not something to design from scratch. | E12: New finding, directly relevant to GV-02
A13: CR-03 verification gotcha: systemd Linger | B13: A real risk that CR-03 ('hermes-gateway running persistently', marked Done) might not be as proven as assumed. | C13: A systemd --user gateway service only survives an actual REBOOT (not just logout) if `loginctl show-user $USER -p Linger` reports Linger=yes. A community walkthrough flagged this as the single most commonly-missed step. Full verification sequence: confirm `systemctl --user status hermes-gateway` is active, confirm Linger=yes, then actually reboot the box and message the bot without logging back in first. | D13: RECOMMEND re-verifying CR-03 with this exact checklist before trusting it's Done -- a service that LOOKS running can still fail to survive a real reboot if linger was never enabled. | E13: Verification gap flagged on a Done row
A14: Telegram gateway: exact verified setup + verify sequence | B14: Closes IA-05 (Telegram channel, Partial) with a concrete, tested command sequence, not just 'get a bot token.' | C14: `hermes gateway setup` (writes config only, does NOT start anything) -> test with `hermes gateway run` in foreground, confirm the log shows 'Connected to Telegram (polling mode)' and 'telegram connected' -> Ctrl-C -> `hermes gateway start` for the real managed service. Polling mode means no inbound firewall port needed beyond SSH (matches CR-04 firewall already active). `hermes gateway install` prompts [Y/n] interactively with no skip flag -- over non-interactive SSH, pipe answers: `printf 'n\nY\n' | hermes gateway install`. | D14: This is the exact remaining procedure for IA-05 -- no more research needed on this row, just execution once the BotFather token exists. | E14: Actionable, directly closes IA-05's remaining steps
A15: SOUL.md: practical template | B15: Directly unblocks IM-01 (SOUL.md committed to hermes-vps, Not Started since the original drafted version was apparently never actually written to the box). | C15: Recommended structure (official starter pattern + community consensus): 4 sections -- Soul (1-2 sentences, who it is), Voice (3-5 lines, tone/style), Operations (3-5 lines, autonomy/decision rules), Restrictions (3-5 lines, hard boundaries). 50-80 lines total (~400-800 tokens/turn). `hermes prompt-size` shows the actual token breakdown once written. `system_message` in config.yaml is a secondary, non-identity slot for rules that don't belong in SOUL.md (API conventions, output format). | D15: Ready to draft and commit -- this was the single biggest blocker on IM-01 (not knowing the right shape/length), now resolved. | E15: Actionable, directly closes IM-01's main blocker
... A19: Credential pools confirmed | B19: Extends SV-16 (Hermes native vault + pools, logged but not detailed). | C19: `hermes auth add <provider> --api-key ...` registers an additional key for a provider already in use; `hermes auth list` shows them. Rotation strategies: fill_first (default), round_robin, least_used, random, set via `credential_pool_strategies` in config.yaml. Tried BEFORE the separate fallback_model config kicks in. | D19: No action needed now -- cheap resilience to add later if any provider (OpenRouter, Anthropic) is ever rate-limited in practice. | E19: Reference, not needed yet
